{
  "attribute": [
    " SMD"
  ], 
  "library_name": "QMS-2X52-SMD", 
  "layer": "15", 
  "attribute1": "00000000", 
  "art": [
    {
      "line_width": 60.0, 
      "startx": 7900.0, 
      "starty": 500.0, 
      "endy": 500.0, 
      "endx": 500.0, 
      "layer": "21", 
      "shape": "segment"
    }, 
    {
      "line_width": 60.0, 
      "startx": 500.0, 
      "starty": -500.0, 
      "endy": -500.0, 
      "endx": 7900.0, 
      "layer": "21", 
      "shape": "segment"
    }, 
    {
      "line_width": 60.0, 
      "startx": -500.0, 
      "starty": 500.0, 
      "endy": 500.0, 
      "endx": -7900.0, 
      "layer": "21", 
      "shape": "segment"
    }, 
    {
      "line_width": 60.0, 
      "startx": -7900.0, 
      "starty": -500.0, 
      "endy": -500.0, 
      "endx": -500.0, 
      "layer": "21", 
      "shape": "segment"
    }, 
    {
      "line_width": 60.0, 
      "startx": -500.0, 
      "starty": 500.0, 
      "endy": -500.0, 
      "endx": -500.0, 
      "layer": "21", 
      "shape": "segment"
    }, 
    {
      "line_width": 60.0, 
      "startx": -7900.0, 
      "starty": -500.0, 
      "endy": 500.0, 
      "endx": -7900.0, 
      "layer": "21", 
      "shape": "segment"
    }, 
    {
      "line_width": 60.0, 
      "startx": 7900.0, 
      "starty": -500.0, 
      "endy": 500.0, 
      "endx": 7900.0, 
      "layer": "21", 
      "shape": "segment"
    }, 
    {
      "line_width": 60.0, 
      "startx": 500.0, 
      "starty": 500.0, 
      "endy": -500.0, 
      "endx": 500.0, 
      "layer": "21", 
      "shape": "segment"
    }, 
    {
      "line_width": 60.0, 
      "startx": 8800.0, 
      "starty": -1700.0, 
      "endy": 1700.0, 
      "endx": 8800.0, 
      "layer": "21", 
      "shape": "segment"
    }, 
    {
      "line_width": 60.0, 
      "startx": 8800.0, 
      "starty": 1700.0, 
      "endy": 1700.0, 
      "endx": 7600.0, 
      "layer": "21", 
      "shape": "segment"
    }, 
    {
      "line_width": 60.0, 
      "startx": 7600.0, 
      "starty": 1700.0, 
      "endy": 1500.0, 
      "endx": 7600.0, 
      "layer": "21", 
      "shape": "segment"
    }, 
    {
      "line_width": 60.0, 
      "startx": 800.0, 
      "starty": 1500.0, 
      "endy": 1700.0, 
      "endx": 800.0, 
      "layer": "21", 
      "shape": "segment"
    }, 
    {
      "line_width": 60.0, 
      "startx": 800.0, 
      "starty": 1700.0, 
      "endy": 1700.0, 
      "endx": -800.0, 
      "layer": "21", 
      "shape": "segment"
    }, 
    {
      "line_width": 60.0, 
      "startx": -800.0, 
      "starty": 1700.0, 
      "endy": 1500.0, 
      "endx": -800.0, 
      "layer": "21", 
      "shape": "segment"
    }, 
    {
      "line_width": 60.0, 
      "startx": -7600.0, 
      "starty": 1500.0, 
      "endy": 1700.0, 
      "endx": -7600.0, 
      "layer": "21", 
      "shape": "segment"
    }, 
    {
      "line_width": 60.0, 
      "startx": -7600.0, 
      "starty": 1700.0, 
      "endy": 1700.0, 
      "endx": -8800.0, 
      "layer": "21", 
      "shape": "segment"
    }, 
    {
      "line_width": 60.0, 
      "startx": -8800.0, 
      "starty": 1700.0, 
      "endy": -1700.0, 
      "endx": -8800.0, 
      "layer": "21", 
      "shape": "segment"
    }, 
    {
      "line_width": 60.0, 
      "startx": -8800.0, 
      "starty": -1700.0, 
      "endy": -1700.0, 
      "endx": -7600.0, 
      "layer": "21", 
      "shape": "segment"
    }, 
    {
      "line_width": 60.0, 
      "startx": -7600.0, 
      "starty": -1700.0, 
      "endy": -1500.0, 
      "endx": -7600.0, 
      "layer": "21", 
      "shape": "segment"
    }, 
    {
      "line_width": 60.0, 
      "startx": -800.0, 
      "starty": -1500.0, 
      "endy": -1700.0, 
      "endx": -800.0, 
      "layer": "21", 
      "shape": "segment"
    }, 
    {
      "line_width": 60.0, 
      "startx": -800.0, 
      "starty": -1700.0, 
      "endy": -1700.0, 
      "endx": 800.0, 
      "layer": "21", 
      "shape": "segment"
    }, 
    {
      "line_width": 60.0, 
      "startx": 800.0, 
      "starty": -1700.0, 
      "endy": -1500.0, 
      "endx": 800.0, 
      "layer": "21", 
      "shape": "segment"
    }, 
    {
      "line_width": 60.0, 
      "startx": 7600.0, 
      "starty": -1500.0, 
      "endy": -1700.0, 
      "endx": 7600.0, 
      "layer": "21", 
      "shape": "segment"
    }, 
    {
      "line_width": 60.0, 
      "startx": 7600.0, 
      "starty": -1700.0, 
      "endy": -1700.0, 
      "endx": 8800.0, 
      "layer": "21", 
      "shape": "segment"
    }, 
    {
      "line_width": 60.0, 
      "layer": "21", 
      "shape": "circle", 
      "r": 450.0, 
      "y": 0.0, 
      "x": 0.0
    }
  ], 
  "name": "QMS-2X52-SMD", 
  "text": [
    {
      "layer": "21", 
      "angle": 1.5707963267948966, 
      "misc": " N \"Ref**\"", 
      "sizex": 500.0, 
      "number": "0", 
      "sizey": 350.0, 
      "visible": true, 
      "flag": "N", 
      "text": "Ref**", 
      "y": -550.0, 
      "x": 8400.0, 
      "rotation": "900", 
      "penwidth": 80.0
    }, 
    {
      "layer": "21", 
      "angle": 0.0, 
      "misc": " N \"QMS-2X52-SMD\"", 
      "sizex": 500.0, 
      "number": "1", 
      "sizey": 350.0, 
      "visible": true, 
      "flag": "N", 
      "text": "QMS-2X52-SMD", 
      "y": -2200.0, 
      "x": 0.0, 
      "rotation": "0", 
      "penwidth": 80.0
    }, 
    {
      "layer": "21", 
      "angle": 0.0, 
      "misc": " N \"2\"", 
      "sizex": 400.0, 
      "number": "2", 
      "sizey": 300.0, 
      "visible": true, 
      "flag": "N", 
      "text": "2", 
      "y": -1339.0, 
      "x": 7953.0, 
      "rotation": "0", 
      "penwidth": 75.0
    }, 
    {
      "layer": "21", 
      "angle": 0.0, 
      "misc": " N \"1\"", 
      "sizex": 400.0, 
      "number": "2", 
      "sizey": 300.0, 
      "visible": true, 
      "flag": "N", 
      "text": "1", 
      "y": 1299.0, 
      "x": 7874.0, 
      "rotation": "0", 
      "penwidth": 75.0
    }
  ], 
  "timestamp_op": "0", 
  "rotation_cost_180": "0", 
  "attribute2": "~~", 
  "y": 0.0, 
  "rotation_cost_misc": "0", 
  "pad": [
    {
      "net_name": "", 
      "angle": 0.0, 
      "name": "1", 
      "drill_diam": 0.0, 
      "deltax": 0.0, 
      "deltay": 0.0, 
      "sizex": 150.0, 
      "sizey": 850.0, 
      "drill_x": 0.0, 
      "layer_mask": "00888000", 
      "shape": "rectangle", 
      "net_number": "0", 
      "drill_y": 0.0, 
      "posy": 1300.0, 
      "posx": 7325.0, 
      "shape_code": "R", 
      "type": "SMD", 
      "drill_shape": "circle", 
      "orientation": 0
    }, 
    {
      "net_name": "", 
      "angle": 0.0, 
      "name": "2", 
      "drill_diam": 0.0, 
      "deltax": 0.0, 
      "deltay": 0.0, 
      "sizex": 150.0, 
      "sizey": 850.0, 
      "drill_x": 0.0, 
      "layer_mask": "00888000", 
      "shape": "rectangle", 
      "net_number": "0", 
      "drill_y": 0.0, 
      "posy": -1300.0, 
      "posx": 7325.0, 
      "shape_code": "R", 
      "type": "SMD", 
      "drill_shape": "circle", 
      "orientation": 0
    }, 
    {
      "net_name": "", 
      "angle": 0.0, 
      "name": "3", 
      "drill_diam": 0.0, 
      "deltax": 0.0, 
      "deltay": 0.0, 
      "sizex": 150.0, 
      "sizey": 850.0, 
      "drill_x": 0.0, 
      "layer_mask": "00888000", 
      "shape": "rectangle", 
      "net_number": "0", 
      "drill_y": 0.0, 
      "posy": 1300.0, 
      "posx": 7075.0, 
      "shape_code": "R", 
      "type": "SMD", 
      "drill_shape": "circle", 
      "orientation": 0
    }, 
    {
      "net_name": "", 
      "angle": 0.0, 
      "name": "4", 
      "drill_diam": 0.0, 
      "deltax": 0.0, 
      "deltay": 0.0, 
      "sizex": 150.0, 
      "sizey": 850.0, 
      "drill_x": 0.0, 
      "layer_mask": "00888000", 
      "shape": "rectangle", 
      "net_number": "0", 
      "drill_y": 0.0, 
      "posy": -1300.0, 
      "posx": 7075.0, 
      "shape_code": "R", 
      "type": "SMD", 
      "drill_shape": "circle", 
      "orientation": 0
    }, 
    {
      "net_name": "", 
      "angle": 0.0, 
      "name": "5", 
      "drill_diam": 0.0, 
      "deltax": 0.0, 
      "deltay": 0.0, 
      "sizex": 150.0, 
      "sizey": 850.0, 
      "drill_x": 0.0, 
      "layer_mask": "00888000", 
      "shape": "rectangle", 
      "net_number": "0", 
      "drill_y": 0.0, 
      "posy": 1300.0, 
      "posx": 6825.0, 
      "shape_code": "R", 
      "type": "SMD", 
      "drill_shape": "circle", 
      "orientation": 0
    }, 
    {
      "net_name": "", 
      "angle": 0.0, 
      "name": "6", 
      "drill_diam": 0.0, 
      "deltax": 0.0, 
      "deltay": 0.0, 
      "sizex": 150.0, 
      "sizey": 850.0, 
      "drill_x": 0.0, 
      "layer_mask": "00888000", 
      "shape": "rectangle", 
      "net_number": "0", 
      "drill_y": 0.0, 
      "posy": -1300.0, 
      "posx": 6825.0, 
      "shape_code": "R", 
      "type": "SMD", 
      "drill_shape": "circle", 
      "orientation": 0
    }, 
    {
      "net_name": "", 
      "angle": 0.0, 
      "name": "7", 
      "drill_diam": 0.0, 
      "deltax": 0.0, 
      "deltay": 0.0, 
      "sizex": 150.0, 
      "sizey": 850.0, 
      "drill_x": 0.0, 
      "layer_mask": "00888000", 
      "shape": "rectangle", 
      "net_number": "0", 
      "drill_y": 0.0, 
      "posy": 1300.0, 
      "posx": 6575.0, 
      "shape_code": "R", 
      "type": "SMD", 
      "drill_shape": "circle", 
      "orientation": 0
    }, 
    {
      "net_name": "", 
      "angle": 0.0, 
      "name": "8", 
      "drill_diam": 0.0, 
      "deltax": 0.0, 
      "deltay": 0.0, 
      "sizex": 150.0, 
      "sizey": 850.0, 
      "drill_x": 0.0, 
      "layer_mask": "00888000", 
      "shape": "rectangle", 
      "net_number": "0", 
      "drill_y": 0.0, 
      "posy": -1300.0, 
      "posx": 6575.0, 
      "shape_code": "R", 
      "type": "SMD", 
      "drill_shape": "circle", 
      "orientation": 0
    }, 
    {
      "net_name": "", 
      "angle": 0.0, 
      "name": "9", 
      "drill_diam": 0.0, 
      "deltax": 0.0, 
      "deltay": 0.0, 
      "sizex": 150.0, 
      "sizey": 850.0, 
      "drill_x": 0.0, 
      "layer_mask": "00888000", 
      "shape": "rectangle", 
      "net_number": "0", 
      "drill_y": 0.0, 
      "posy": 1300.0, 
      "posx": 6325.0, 
      "shape_code": "R", 
      "type": "SMD", 
      "drill_shape": "circle", 
      "orientation": 0
    }, 
    {
      "net_name": "", 
      "angle": 0.0, 
      "name": "10", 
      "drill_diam": 0.0, 
      "deltax": 0.0, 
      "deltay": 0.0, 
      "sizex": 150.0, 
      "sizey": 850.0, 
      "drill_x": 0.0, 
      "layer_mask": "00888000", 
      "shape": "rectangle", 
      "net_number": "0", 
      "drill_y": 0.0, 
      "posy": -1300.0, 
      "posx": 6325.0, 
      "shape_code": "R", 
      "type": "SMD", 
      "drill_shape": "circle", 
      "orientation": 0
    }, 
    {
      "net_name": "", 
      "angle": 0.0, 
      "name": "11", 
      "drill_diam": 0.0, 
      "deltax": 0.0, 
      "deltay": 0.0, 
      "sizex": 150.0, 
      "sizey": 850.0, 
      "drill_x": 0.0, 
      "layer_mask": "00888000", 
      "shape": "rectangle", 
      "net_number": "0", 
      "drill_y": 0.0, 
      "posy": 1300.0, 
      "posx": 6075.0, 
      "shape_code": "R", 
      "type": "SMD", 
      "drill_shape": "circle", 
      "orientation": 0
    }, 
    {
      "net_name": "", 
      "angle": 0.0, 
      "name": "12", 
      "drill_diam": 0.0, 
      "deltax": 0.0, 
      "deltay": 0.0, 
      "sizex": 150.0, 
      "sizey": 850.0, 
      "drill_x": 0.0, 
      "layer_mask": "00888000", 
      "shape": "rectangle", 
      "net_number": "0", 
      "drill_y": 0.0, 
      "posy": -1300.0, 
      "posx": 6075.0, 
      "shape_code": "R", 
      "type": "SMD", 
      "drill_shape": "circle", 
      "orientation": 0
    }, 
    {
      "net_name": "", 
      "angle": 0.0, 
      "name": "13", 
      "drill_diam": 0.0, 
      "deltax": 0.0, 
      "deltay": 0.0, 
      "sizex": 150.0, 
      "sizey": 850.0, 
      "drill_x": 0.0, 
      "layer_mask": "00888000", 
      "shape": "rectangle", 
      "net_number": "0", 
      "drill_y": 0.0, 
      "posy": 1300.0, 
      "posx": 5825.0, 
      "shape_code": "R", 
      "type": "SMD", 
      "drill_shape": "circle", 
      "orientation": 0
    }, 
    {
      "net_name": "", 
      "angle": 0.0, 
      "name": "14", 
      "drill_diam": 0.0, 
      "deltax": 0.0, 
      "deltay": 0.0, 
      "sizex": 150.0, 
      "sizey": 850.0, 
      "drill_x": 0.0, 
      "layer_mask": "00888000", 
      "shape": "rectangle", 
      "net_number": "0", 
      "drill_y": 0.0, 
      "posy": -1300.0, 
      "posx": 5825.0, 
      "shape_code": "R", 
      "type": "SMD", 
      "drill_shape": "circle", 
      "orientation": 0
    }, 
    {
      "net_name": "", 
      "angle": 0.0, 
      "name": "15", 
      "drill_diam": 0.0, 
      "deltax": 0.0, 
      "deltay": 0.0, 
      "sizex": 150.0, 
      "sizey": 850.0, 
      "drill_x": 0.0, 
      "layer_mask": "00888000", 
      "shape": "rectangle", 
      "net_number": "0", 
      "drill_y": 0.0, 
      "posy": 1300.0, 
      "posx": 5575.0, 
      "shape_code": "R", 
      "type": "SMD", 
      "drill_shape": "circle", 
      "orientation": 0
    }, 
    {
      "net_name": "", 
      "angle": 0.0, 
      "name": "16", 
      "drill_diam": 0.0, 
      "deltax": 0.0, 
      "deltay": 0.0, 
      "sizex": 150.0, 
      "sizey": 850.0, 
      "drill_x": 0.0, 
      "layer_mask": "00888000", 
      "shape": "rectangle", 
      "net_number": "0", 
      "drill_y": 0.0, 
      "posy": -1300.0, 
      "posx": 5575.0, 
      "shape_code": "R", 
      "type": "SMD", 
      "drill_shape": "circle", 
      "orientation": 0
    }, 
    {
      "net_name": "", 
      "angle": 0.0, 
      "name": "17", 
      "drill_diam": 0.0, 
      "deltax": 0.0, 
      "deltay": 0.0, 
      "sizex": 150.0, 
      "sizey": 850.0, 
      "drill_x": 0.0, 
      "layer_mask": "00888000", 
      "shape": "rectangle", 
      "net_number": "0", 
      "drill_y": 0.0, 
      "posy": 1300.0, 
      "posx": 5325.0, 
      "shape_code": "R", 
      "type": "SMD", 
      "drill_shape": "circle", 
      "orientation": 0
    }, 
    {
      "net_name": "", 
      "angle": 0.0, 
      "name": "18", 
      "drill_diam": 0.0, 
      "deltax": 0.0, 
      "deltay": 0.0, 
      "sizex": 150.0, 
      "sizey": 850.0, 
      "drill_x": 0.0, 
      "layer_mask": "00888000", 
      "shape": "rectangle", 
      "net_number": "0", 
      "drill_y": 0.0, 
      "posy": -1300.0, 
      "posx": 5325.0, 
      "shape_code": "R", 
      "type": "SMD", 
      "drill_shape": "circle", 
      "orientation": 0
    }, 
    {
      "net_name": "", 
      "angle": 0.0, 
      "name": "19", 
      "drill_diam": 0.0, 
      "deltax": 0.0, 
      "deltay": 0.0, 
      "sizex": 150.0, 
      "sizey": 850.0, 
      "drill_x": 0.0, 
      "layer_mask": "00888000", 
      "shape": "rectangle", 
      "net_number": "0", 
      "drill_y": 0.0, 
      "posy": 1300.0, 
      "posx": 5075.0, 
      "shape_code": "R", 
      "type": "SMD", 
      "drill_shape": "circle", 
      "orientation": 0
    }, 
    {
      "net_name": "", 
      "angle": 0.0, 
      "name": "20", 
      "drill_diam": 0.0, 
      "deltax": 0.0, 
      "deltay": 0.0, 
      "sizex": 150.0, 
      "sizey": 850.0, 
      "drill_x": 0.0, 
      "layer_mask": "00888000", 
      "shape": "rectangle", 
      "net_number": "0", 
      "drill_y": 0.0, 
      "posy": -1300.0, 
      "posx": 5075.0, 
      "shape_code": "R", 
      "type": "SMD", 
      "drill_shape": "circle", 
      "orientation": 0
    }, 
    {
      "net_name": "", 
      "angle": 0.0, 
      "name": "21", 
      "drill_diam": 0.0, 
      "deltax": 0.0, 
      "deltay": 0.0, 
      "sizex": 150.0, 
      "sizey": 850.0, 
      "drill_x": 0.0, 
      "layer_mask": "00888000", 
      "shape": "rectangle", 
      "net_number": "0", 
      "drill_y": 0.0, 
      "posy": 1300.0, 
      "posx": 4825.0, 
      "shape_code": "R", 
      "type": "SMD", 
      "drill_shape": "circle", 
      "orientation": 0
    }, 
    {
      "net_name": "", 
      "angle": 0.0, 
      "name": "22", 
      "drill_diam": 0.0, 
      "deltax": 0.0, 
      "deltay": 0.0, 
      "sizex": 150.0, 
      "sizey": 850.0, 
      "drill_x": 0.0, 
      "layer_mask": "00888000", 
      "shape": "rectangle", 
      "net_number": "0", 
      "drill_y": 0.0, 
      "posy": -1300.0, 
      "posx": 4825.0, 
      "shape_code": "R", 
      "type": "SMD", 
      "drill_shape": "circle", 
      "orientation": 0
    }, 
    {
      "net_name": "", 
      "angle": 0.0, 
      "name": "23", 
      "drill_diam": 0.0, 
      "deltax": 0.0, 
      "deltay": 0.0, 
      "sizex": 150.0, 
      "sizey": 850.0, 
      "drill_x": 0.0, 
      "layer_mask": "00888000", 
      "shape": "rectangle", 
      "net_number": "0", 
      "drill_y": 0.0, 
      "posy": 1300.0, 
      "posx": 4575.0, 
      "shape_code": "R", 
      "type": "SMD", 
      "drill_shape": "circle", 
      "orientation": 0
    }, 
    {
      "net_name": "", 
      "angle": 0.0, 
      "name": "24", 
      "drill_diam": 0.0, 
      "deltax": 0.0, 
      "deltay": 0.0, 
      "sizex": 150.0, 
      "sizey": 850.0, 
      "drill_x": 0.0, 
      "layer_mask": "00888000", 
      "shape": "rectangle", 
      "net_number": "0", 
      "drill_y": 0.0, 
      "posy": -1300.0, 
      "posx": 4575.0, 
      "shape_code": "R", 
      "type": "SMD", 
      "drill_shape": "circle", 
      "orientation": 0
    }, 
    {
      "net_name": "", 
      "angle": 0.0, 
      "name": "25", 
      "drill_diam": 0.0, 
      "deltax": 0.0, 
      "deltay": 0.0, 
      "sizex": 150.0, 
      "sizey": 850.0, 
      "drill_x": 0.0, 
      "layer_mask": "00888000", 
      "shape": "rectangle", 
      "net_number": "0", 
      "drill_y": 0.0, 
      "posy": 1300.0, 
      "posx": 4325.0, 
      "shape_code": "R", 
      "type": "SMD", 
      "drill_shape": "circle", 
      "orientation": 0
    }, 
    {
      "net_name": "", 
      "angle": 0.0, 
      "name": "26", 
      "drill_diam": 0.0, 
      "deltax": 0.0, 
      "deltay": 0.0, 
      "sizex": 150.0, 
      "sizey": 850.0, 
      "drill_x": 0.0, 
      "layer_mask": "00888000", 
      "shape": "rectangle", 
      "net_number": "0", 
      "drill_y": 0.0, 
      "posy": -1300.0, 
      "posx": 4325.0, 
      "shape_code": "R", 
      "type": "SMD", 
      "drill_shape": "circle", 
      "orientation": 0
    }, 
    {
      "net_name": "", 
      "angle": 0.0, 
      "name": "27", 
      "drill_diam": 0.0, 
      "deltax": 0.0, 
      "deltay": 0.0, 
      "sizex": 150.0, 
      "sizey": 850.0, 
      "drill_x": 0.0, 
      "layer_mask": "00888000", 
      "shape": "rectangle", 
      "net_number": "0", 
      "drill_y": 0.0, 
      "posy": 1300.0, 
      "posx": 4075.0, 
      "shape_code": "R", 
      "type": "SMD", 
      "drill_shape": "circle", 
      "orientation": 0
    }, 
    {
      "net_name": "", 
      "angle": 0.0, 
      "name": "28", 
      "drill_diam": 0.0, 
      "deltax": 0.0, 
      "deltay": 0.0, 
      "sizex": 150.0, 
      "sizey": 850.0, 
      "drill_x": 0.0, 
      "layer_mask": "00888000", 
      "shape": "rectangle", 
      "net_number": "0", 
      "drill_y": 0.0, 
      "posy": -1300.0, 
      "posx": 4075.0, 
      "shape_code": "R", 
      "type": "SMD", 
      "drill_shape": "circle", 
      "orientation": 0
    }, 
    {
      "net_name": "", 
      "angle": 0.0, 
      "name": "29", 
      "drill_diam": 0.0, 
      "deltax": 0.0, 
      "deltay": 0.0, 
      "sizex": 150.0, 
      "sizey": 850.0, 
      "drill_x": 0.0, 
      "layer_mask": "00888000", 
      "shape": "rectangle", 
      "net_number": "0", 
      "drill_y": 0.0, 
      "posy": 1300.0, 
      "posx": 3825.0, 
      "shape_code": "R", 
      "type": "SMD", 
      "drill_shape": "circle", 
      "orientation": 0
    }, 
    {
      "net_name": "", 
      "angle": 0.0, 
      "name": "30", 
      "drill_diam": 0.0, 
      "deltax": 0.0, 
      "deltay": 0.0, 
      "sizex": 150.0, 
      "sizey": 850.0, 
      "drill_x": 0.0, 
      "layer_mask": "00888000", 
      "shape": "rectangle", 
      "net_number": "0", 
      "drill_y": 0.0, 
      "posy": -1300.0, 
      "posx": 3825.0, 
      "shape_code": "R", 
      "type": "SMD", 
      "drill_shape": "circle", 
      "orientation": 0
    }, 
    {
      "net_name": "", 
      "angle": 0.0, 
      "name": "31", 
      "drill_diam": 0.0, 
      "deltax": 0.0, 
      "deltay": 0.0, 
      "sizex": 150.0, 
      "sizey": 850.0, 
      "drill_x": 0.0, 
      "layer_mask": "00888000", 
      "shape": "rectangle", 
      "net_number": "0", 
      "drill_y": 0.0, 
      "posy": 1300.0, 
      "posx": 3575.0, 
      "shape_code": "R", 
      "type": "SMD", 
      "drill_shape": "circle", 
      "orientation": 0
    }, 
    {
      "net_name": "", 
      "angle": 0.0, 
      "name": "32", 
      "drill_diam": 0.0, 
      "deltax": 0.0, 
      "deltay": 0.0, 
      "sizex": 150.0, 
      "sizey": 850.0, 
      "drill_x": 0.0, 
      "layer_mask": "00888000", 
      "shape": "rectangle", 
      "net_number": "0", 
      "drill_y": 0.0, 
      "posy": -1300.0, 
      "posx": 3575.0, 
      "shape_code": "R", 
      "type": "SMD", 
      "drill_shape": "circle", 
      "orientation": 0
    }, 
    {
      "net_name": "", 
      "angle": 0.0, 
      "name": "33", 
      "drill_diam": 0.0, 
      "deltax": 0.0, 
      "deltay": 0.0, 
      "sizex": 150.0, 
      "sizey": 850.0, 
      "drill_x": 0.0, 
      "layer_mask": "00888000", 
      "shape": "rectangle", 
      "net_number": "0", 
      "drill_y": 0.0, 
      "posy": 1300.0, 
      "posx": 3325.0, 
      "shape_code": "R", 
      "type": "SMD", 
      "drill_shape": "circle", 
      "orientation": 0
    }, 
    {
      "net_name": "", 
      "angle": 0.0, 
      "name": "34", 
      "drill_diam": 0.0, 
      "deltax": 0.0, 
      "deltay": 0.0, 
      "sizex": 150.0, 
      "sizey": 850.0, 
      "drill_x": 0.0, 
      "layer_mask": "00888000", 
      "shape": "rectangle", 
      "net_number": "0", 
      "drill_y": 0.0, 
      "posy": -1300.0, 
      "posx": 3325.0, 
      "shape_code": "R", 
      "type": "SMD", 
      "drill_shape": "circle", 
      "orientation": 0
    }, 
    {
      "net_name": "", 
      "angle": 0.0, 
      "name": "35", 
      "drill_diam": 0.0, 
      "deltax": 0.0, 
      "deltay": 0.0, 
      "sizex": 150.0, 
      "sizey": 850.0, 
      "drill_x": 0.0, 
      "layer_mask": "00888000", 
      "shape": "rectangle", 
      "net_number": "0", 
      "drill_y": 0.0, 
      "posy": 1300.0, 
      "posx": 3075.0, 
      "shape_code": "R", 
      "type": "SMD", 
      "drill_shape": "circle", 
      "orientation": 0
    }, 
    {
      "net_name": "", 
      "angle": 0.0, 
      "name": "36", 
      "drill_diam": 0.0, 
      "deltax": 0.0, 
      "deltay": 0.0, 
      "sizex": 150.0, 
      "sizey": 850.0, 
      "drill_x": 0.0, 
      "layer_mask": "00888000", 
      "shape": "rectangle", 
      "net_number": "0", 
      "drill_y": 0.0, 
      "posy": -1300.0, 
      "posx": 3075.0, 
      "shape_code": "R", 
      "type": "SMD", 
      "drill_shape": "circle", 
      "orientation": 0
    }, 
    {
      "net_name": "", 
      "angle": 0.0, 
      "name": "37", 
      "drill_diam": 0.0, 
      "deltax": 0.0, 
      "deltay": 0.0, 
      "sizex": 150.0, 
      "sizey": 850.0, 
      "drill_x": 0.0, 
      "layer_mask": "00888000", 
      "shape": "rectangle", 
      "net_number": "0", 
      "drill_y": 0.0, 
      "posy": 1300.0, 
      "posx": 2825.0, 
      "shape_code": "R", 
      "type": "SMD", 
      "drill_shape": "circle", 
      "orientation": 0
    }, 
    {
      "net_name": "", 
      "angle": 0.0, 
      "name": "38", 
      "drill_diam": 0.0, 
      "deltax": 0.0, 
      "deltay": 0.0, 
      "sizex": 150.0, 
      "sizey": 850.0, 
      "drill_x": 0.0, 
      "layer_mask": "00888000", 
      "shape": "rectangle", 
      "net_number": "0", 
      "drill_y": 0.0, 
      "posy": -1300.0, 
      "posx": 2825.0, 
      "shape_code": "R", 
      "type": "SMD", 
      "drill_shape": "circle", 
      "orientation": 0
    }, 
    {
      "net_name": "", 
      "angle": 0.0, 
      "name": "39", 
      "drill_diam": 0.0, 
      "deltax": 0.0, 
      "deltay": 0.0, 
      "sizex": 150.0, 
      "sizey": 850.0, 
      "drill_x": 0.0, 
      "layer_mask": "00888000", 
      "shape": "rectangle", 
      "net_number": "0", 
      "drill_y": 0.0, 
      "posy": 1300.0, 
      "posx": 2575.0, 
      "shape_code": "R", 
      "type": "SMD", 
      "drill_shape": "circle", 
      "orientation": 0
    }, 
    {
      "net_name": "", 
      "angle": 0.0, 
      "name": "40", 
      "drill_diam": 0.0, 
      "deltax": 0.0, 
      "deltay": 0.0, 
      "sizex": 150.0, 
      "sizey": 850.0, 
      "drill_x": 0.0, 
      "layer_mask": "00888000", 
      "shape": "rectangle", 
      "net_number": "0", 
      "drill_y": 0.0, 
      "posy": -1300.0, 
      "posx": 2575.0, 
      "shape_code": "R", 
      "type": "SMD", 
      "drill_shape": "circle", 
      "orientation": 0
    }, 
    {
      "net_name": "", 
      "angle": 0.0, 
      "name": "41", 
      "drill_diam": 0.0, 
      "deltax": 0.0, 
      "deltay": 0.0, 
      "sizex": 150.0, 
      "sizey": 850.0, 
      "drill_x": 0.0, 
      "layer_mask": "00888000", 
      "shape": "rectangle", 
      "net_number": "0", 
      "drill_y": 0.0, 
      "posy": 1300.0, 
      "posx": 2325.0, 
      "shape_code": "R", 
      "type": "SMD", 
      "drill_shape": "circle", 
      "orientation": 0
    }, 
    {
      "net_name": "", 
      "angle": 0.0, 
      "name": "42", 
      "drill_diam": 0.0, 
      "deltax": 0.0, 
      "deltay": 0.0, 
      "sizex": 150.0, 
      "sizey": 850.0, 
      "drill_x": 0.0, 
      "layer_mask": "00888000", 
      "shape": "rectangle", 
      "net_number": "0", 
      "drill_y": 0.0, 
      "posy": -1300.0, 
      "posx": 2325.0, 
      "shape_code": "R", 
      "type": "SMD", 
      "drill_shape": "circle", 
      "orientation": 0
    }, 
    {
      "net_name": "", 
      "angle": 0.0, 
      "name": "43", 
      "drill_diam": 0.0, 
      "deltax": 0.0, 
      "deltay": 0.0, 
      "sizex": 150.0, 
      "sizey": 850.0, 
      "drill_x": 0.0, 
      "layer_mask": "00888000", 
      "shape": "rectangle", 
      "net_number": "0", 
      "drill_y": 0.0, 
      "posy": 1300.0, 
      "posx": 2075.0, 
      "shape_code": "R", 
      "type": "SMD", 
      "drill_shape": "circle", 
      "orientation": 0
    }, 
    {
      "net_name": "", 
      "angle": 0.0, 
      "name": "44", 
      "drill_diam": 0.0, 
      "deltax": 0.0, 
      "deltay": 0.0, 
      "sizex": 150.0, 
      "sizey": 850.0, 
      "drill_x": 0.0, 
      "layer_mask": "00888000", 
      "shape": "rectangle", 
      "net_number": "0", 
      "drill_y": 0.0, 
      "posy": -1300.0, 
      "posx": 2075.0, 
      "shape_code": "R", 
      "type": "SMD", 
      "drill_shape": "circle", 
      "orientation": 0
    }, 
    {
      "net_name": "", 
      "angle": 0.0, 
      "name": "45", 
      "drill_diam": 0.0, 
      "deltax": 0.0, 
      "deltay": 0.0, 
      "sizex": 150.0, 
      "sizey": 850.0, 
      "drill_x": 0.0, 
      "layer_mask": "00888000", 
      "shape": "rectangle", 
      "net_number": "0", 
      "drill_y": 0.0, 
      "posy": 1300.0, 
      "posx": 1825.0, 
      "shape_code": "R", 
      "type": "SMD", 
      "drill_shape": "circle", 
      "orientation": 0
    }, 
    {
      "net_name": "", 
      "angle": 0.0, 
      "name": "46", 
      "drill_diam": 0.0, 
      "deltax": 0.0, 
      "deltay": 0.0, 
      "sizex": 150.0, 
      "sizey": 850.0, 
      "drill_x": 0.0, 
      "layer_mask": "00888000", 
      "shape": "rectangle", 
      "net_number": "0", 
      "drill_y": 0.0, 
      "posy": -1300.0, 
      "posx": 1825.0, 
      "shape_code": "R", 
      "type": "SMD", 
      "drill_shape": "circle", 
      "orientation": 0
    }, 
    {
      "net_name": "", 
      "angle": 0.0, 
      "name": "47", 
      "drill_diam": 0.0, 
      "deltax": 0.0, 
      "deltay": 0.0, 
      "sizex": 150.0, 
      "sizey": 850.0, 
      "drill_x": 0.0, 
      "layer_mask": "00888000", 
      "shape": "rectangle", 
      "net_number": "0", 
      "drill_y": 0.0, 
      "posy": 1300.0, 
      "posx": 1575.0, 
      "shape_code": "R", 
      "type": "SMD", 
      "drill_shape": "circle", 
      "orientation": 0
    }, 
    {
      "net_name": "", 
      "angle": 0.0, 
      "name": "48", 
      "drill_diam": 0.0, 
      "deltax": 0.0, 
      "deltay": 0.0, 
      "sizex": 150.0, 
      "sizey": 850.0, 
      "drill_x": 0.0, 
      "layer_mask": "00888000", 
      "shape": "rectangle", 
      "net_number": "0", 
      "drill_y": 0.0, 
      "posy": -1300.0, 
      "posx": 1575.0, 
      "shape_code": "R", 
      "type": "SMD", 
      "drill_shape": "circle", 
      "orientation": 0
    }, 
    {
      "net_name": "", 
      "angle": 0.0, 
      "name": "49", 
      "drill_diam": 0.0, 
      "deltax": 0.0, 
      "deltay": 0.0, 
      "sizex": 150.0, 
      "sizey": 850.0, 
      "drill_x": 0.0, 
      "layer_mask": "00888000", 
      "shape": "rectangle", 
      "net_number": "0", 
      "drill_y": 0.0, 
      "posy": 1300.0, 
      "posx": 1325.0, 
      "shape_code": "R", 
      "type": "SMD", 
      "drill_shape": "circle", 
      "orientation": 0
    }, 
    {
      "net_name": "", 
      "angle": 0.0, 
      "name": "50", 
      "drill_diam": 0.0, 
      "deltax": 0.0, 
      "deltay": 0.0, 
      "sizex": 150.0, 
      "sizey": 850.0, 
      "drill_x": 0.0, 
      "layer_mask": "00888000", 
      "shape": "rectangle", 
      "net_number": "0", 
      "drill_y": 0.0, 
      "posy": -1300.0, 
      "posx": 1325.0, 
      "shape_code": "R", 
      "type": "SMD", 
      "drill_shape": "circle", 
      "orientation": 0
    }, 
    {
      "net_name": "", 
      "angle": 0.0, 
      "name": "51", 
      "drill_diam": 0.0, 
      "deltax": 0.0, 
      "deltay": 0.0, 
      "sizex": 150.0, 
      "sizey": 850.0, 
      "drill_x": 0.0, 
      "layer_mask": "00888000", 
      "shape": "rectangle", 
      "net_number": "0", 
      "drill_y": 0.0, 
      "posy": 1300.0, 
      "posx": 1075.0, 
      "shape_code": "R", 
      "type": "SMD", 
      "drill_shape": "circle", 
      "orientation": 0
    }, 
    {
      "net_name": "", 
      "angle": 0.0, 
      "name": "52", 
      "drill_diam": 0.0, 
      "deltax": 0.0, 
      "deltay": 0.0, 
      "sizex": 150.0, 
      "sizey": 850.0, 
      "drill_x": 0.0, 
      "layer_mask": "00888000", 
      "shape": "rectangle", 
      "net_number": "0", 
      "drill_y": 0.0, 
      "posy": -1300.0, 
      "posx": 1075.0, 
      "shape_code": "R", 
      "type": "SMD", 
      "drill_shape": "circle", 
      "orientation": 0
    }, 
    {
      "net_name": "", 
      "angle": 0.0, 
      "name": "53", 
      "drill_diam": 0.0, 
      "deltax": 0.0, 
      "deltay": 0.0, 
      "sizex": 150.0, 
      "sizey": 850.0, 
      "drill_x": 0.0, 
      "layer_mask": "00888000", 
      "shape": "rectangle", 
      "net_number": "0", 
      "drill_y": 0.0, 
      "posy": 1300.0, 
      "posx": -1075.0, 
      "shape_code": "R", 
      "type": "SMD", 
      "drill_shape": "circle", 
      "orientation": 0
    }, 
    {
      "net_name": "", 
      "angle": 0.0, 
      "name": "54", 
      "drill_diam": 0.0, 
      "deltax": 0.0, 
      "deltay": 0.0, 
      "sizex": 150.0, 
      "sizey": 850.0, 
      "drill_x": 0.0, 
      "layer_mask": "00888000", 
      "shape": "rectangle", 
      "net_number": "0", 
      "drill_y": 0.0, 
      "posy": -1300.0, 
      "posx": -1075.0, 
      "shape_code": "R", 
      "type": "SMD", 
      "drill_shape": "circle", 
      "orientation": 0
    }, 
    {
      "net_name": "", 
      "angle": 0.0, 
      "name": "55", 
      "drill_diam": 0.0, 
      "deltax": 0.0, 
      "deltay": 0.0, 
      "sizex": 150.0, 
      "sizey": 850.0, 
      "drill_x": 0.0, 
      "layer_mask": "00888000", 
      "shape": "rectangle", 
      "net_number": "0", 
      "drill_y": 0.0, 
      "posy": 1300.0, 
      "posx": -1325.0, 
      "shape_code": "R", 
      "type": "SMD", 
      "drill_shape": "circle", 
      "orientation": 0
    }, 
    {
      "net_name": "", 
      "angle": 0.0, 
      "name": "56", 
      "drill_diam": 0.0, 
      "deltax": 0.0, 
      "deltay": 0.0, 
      "sizex": 150.0, 
      "sizey": 850.0, 
      "drill_x": 0.0, 
      "layer_mask": "00888000", 
      "shape": "rectangle", 
      "net_number": "0", 
      "drill_y": 0.0, 
      "posy": -1300.0, 
      "posx": -1325.0, 
      "shape_code": "R", 
      "type": "SMD", 
      "drill_shape": "circle", 
      "orientation": 0
    }, 
    {
      "net_name": "", 
      "angle": 0.0, 
      "name": "57", 
      "drill_diam": 0.0, 
      "deltax": 0.0, 
      "deltay": 0.0, 
      "sizex": 150.0, 
      "sizey": 850.0, 
      "drill_x": 0.0, 
      "layer_mask": "00888000", 
      "shape": "rectangle", 
      "net_number": "0", 
      "drill_y": 0.0, 
      "posy": 1300.0, 
      "posx": -1575.0, 
      "shape_code": "R", 
      "type": "SMD", 
      "drill_shape": "circle", 
      "orientation": 0
    }, 
    {
      "net_name": "", 
      "angle": 0.0, 
      "name": "58", 
      "drill_diam": 0.0, 
      "deltax": 0.0, 
      "deltay": 0.0, 
      "sizex": 150.0, 
      "sizey": 850.0, 
      "drill_x": 0.0, 
      "layer_mask": "00888000", 
      "shape": "rectangle", 
      "net_number": "0", 
      "drill_y": 0.0, 
      "posy": -1300.0, 
      "posx": -1575.0, 
      "shape_code": "R", 
      "type": "SMD", 
      "drill_shape": "circle", 
      "orientation": 0
    }, 
    {
      "net_name": "", 
      "angle": 0.0, 
      "name": "59", 
      "drill_diam": 0.0, 
      "deltax": 0.0, 
      "deltay": 0.0, 
      "sizex": 150.0, 
      "sizey": 850.0, 
      "drill_x": 0.0, 
      "layer_mask": "00888000", 
      "shape": "rectangle", 
      "net_number": "0", 
      "drill_y": 0.0, 
      "posy": 1300.0, 
      "posx": -1825.0, 
      "shape_code": "R", 
      "type": "SMD", 
      "drill_shape": "circle", 
      "orientation": 0
    }, 
    {
      "net_name": "", 
      "angle": 0.0, 
      "name": "60", 
      "drill_diam": 0.0, 
      "deltax": 0.0, 
      "deltay": 0.0, 
      "sizex": 150.0, 
      "sizey": 850.0, 
      "drill_x": 0.0, 
      "layer_mask": "00888000", 
      "shape": "rectangle", 
      "net_number": "0", 
      "drill_y": 0.0, 
      "posy": -1300.0, 
      "posx": -1825.0, 
      "shape_code": "R", 
      "type": "SMD", 
      "drill_shape": "circle", 
      "orientation": 0
    }, 
    {
      "net_name": "", 
      "angle": 0.0, 
      "name": "61", 
      "drill_diam": 0.0, 
      "deltax": 0.0, 
      "deltay": 0.0, 
      "sizex": 150.0, 
      "sizey": 850.0, 
      "drill_x": 0.0, 
      "layer_mask": "00888000", 
      "shape": "rectangle", 
      "net_number": "0", 
      "drill_y": 0.0, 
      "posy": 1300.0, 
      "posx": -2075.0, 
      "shape_code": "R", 
      "type": "SMD", 
      "drill_shape": "circle", 
      "orientation": 0
    }, 
    {
      "net_name": "", 
      "angle": 0.0, 
      "name": "62", 
      "drill_diam": 0.0, 
      "deltax": 0.0, 
      "deltay": 0.0, 
      "sizex": 150.0, 
      "sizey": 850.0, 
      "drill_x": 0.0, 
      "layer_mask": "00888000", 
      "shape": "rectangle", 
      "net_number": "0", 
      "drill_y": 0.0, 
      "posy": -1300.0, 
      "posx": -2075.0, 
      "shape_code": "R", 
      "type": "SMD", 
      "drill_shape": "circle", 
      "orientation": 0
    }, 
    {
      "net_name": "", 
      "angle": 0.0, 
      "name": "63", 
      "drill_diam": 0.0, 
      "deltax": 0.0, 
      "deltay": 0.0, 
      "sizex": 150.0, 
      "sizey": 850.0, 
      "drill_x": 0.0, 
      "layer_mask": "00888000", 
      "shape": "rectangle", 
      "net_number": "0", 
      "drill_y": 0.0, 
      "posy": 1300.0, 
      "posx": -2325.0, 
      "shape_code": "R", 
      "type": "SMD", 
      "drill_shape": "circle", 
      "orientation": 0
    }, 
    {
      "net_name": "", 
      "angle": 0.0, 
      "name": "64", 
      "drill_diam": 0.0, 
      "deltax": 0.0, 
      "deltay": 0.0, 
      "sizex": 150.0, 
      "sizey": 850.0, 
      "drill_x": 0.0, 
      "layer_mask": "00888000", 
      "shape": "rectangle", 
      "net_number": "0", 
      "drill_y": 0.0, 
      "posy": -1300.0, 
      "posx": -2325.0, 
      "shape_code": "R", 
      "type": "SMD", 
      "drill_shape": "circle", 
      "orientation": 0
    }, 
    {
      "net_name": "", 
      "angle": 0.0, 
      "name": "65", 
      "drill_diam": 0.0, 
      "deltax": 0.0, 
      "deltay": 0.0, 
      "sizex": 150.0, 
      "sizey": 850.0, 
      "drill_x": 0.0, 
      "layer_mask": "00888000", 
      "shape": "rectangle", 
      "net_number": "0", 
      "drill_y": 0.0, 
      "posy": 1300.0, 
      "posx": -2575.0, 
      "shape_code": "R", 
      "type": "SMD", 
      "drill_shape": "circle", 
      "orientation": 0
    }, 
    {
      "net_name": "", 
      "angle": 0.0, 
      "name": "66", 
      "drill_diam": 0.0, 
      "deltax": 0.0, 
      "deltay": 0.0, 
      "sizex": 150.0, 
      "sizey": 850.0, 
      "drill_x": 0.0, 
      "layer_mask": "00888000", 
      "shape": "rectangle", 
      "net_number": "0", 
      "drill_y": 0.0, 
      "posy": -1300.0, 
      "posx": -2575.0, 
      "shape_code": "R", 
      "type": "SMD", 
      "drill_shape": "circle", 
      "orientation": 0
    }, 
    {
      "net_name": "", 
      "angle": 0.0, 
      "name": "67", 
      "drill_diam": 0.0, 
      "deltax": 0.0, 
      "deltay": 0.0, 
      "sizex": 150.0, 
      "sizey": 850.0, 
      "drill_x": 0.0, 
      "layer_mask": "00888000", 
      "shape": "rectangle", 
      "net_number": "0", 
      "drill_y": 0.0, 
      "posy": 1300.0, 
      "posx": -2825.0, 
      "shape_code": "R", 
      "type": "SMD", 
      "drill_shape": "circle", 
      "orientation": 0
    }, 
    {
      "net_name": "", 
      "angle": 0.0, 
      "name": "68", 
      "drill_diam": 0.0, 
      "deltax": 0.0, 
      "deltay": 0.0, 
      "sizex": 150.0, 
      "sizey": 850.0, 
      "drill_x": 0.0, 
      "layer_mask": "00888000", 
      "shape": "rectangle", 
      "net_number": "0", 
      "drill_y": 0.0, 
      "posy": -1300.0, 
      "posx": -2825.0, 
      "shape_code": "R", 
      "type": "SMD", 
      "drill_shape": "circle", 
      "orientation": 0
    }, 
    {
      "net_name": "", 
      "angle": 0.0, 
      "name": "69", 
      "drill_diam": 0.0, 
      "deltax": 0.0, 
      "deltay": 0.0, 
      "sizex": 150.0, 
      "sizey": 850.0, 
      "drill_x": 0.0, 
      "layer_mask": "00888000", 
      "shape": "rectangle", 
      "net_number": "0", 
      "drill_y": 0.0, 
      "posy": 1300.0, 
      "posx": -3075.0, 
      "shape_code": "R", 
      "type": "SMD", 
      "drill_shape": "circle", 
      "orientation": 0
    }, 
    {
      "net_name": "", 
      "angle": 0.0, 
      "name": "70", 
      "drill_diam": 0.0, 
      "deltax": 0.0, 
      "deltay": 0.0, 
      "sizex": 150.0, 
      "sizey": 850.0, 
      "drill_x": 0.0, 
      "layer_mask": "00888000", 
      "shape": "rectangle", 
      "net_number": "0", 
      "drill_y": 0.0, 
      "posy": -1300.0, 
      "posx": -3075.0, 
      "shape_code": "R", 
      "type": "SMD", 
      "drill_shape": "circle", 
      "orientation": 0
    }, 
    {
      "net_name": "", 
      "angle": 0.0, 
      "name": "71", 
      "drill_diam": 0.0, 
      "deltax": 0.0, 
      "deltay": 0.0, 
      "sizex": 150.0, 
      "sizey": 850.0, 
      "drill_x": 0.0, 
      "layer_mask": "00888000", 
      "shape": "rectangle", 
      "net_number": "0", 
      "drill_y": 0.0, 
      "posy": 1300.0, 
      "posx": -3325.0, 
      "shape_code": "R", 
      "type": "SMD", 
      "drill_shape": "circle", 
      "orientation": 0
    }, 
    {
      "net_name": "", 
      "angle": 0.0, 
      "name": "72", 
      "drill_diam": 0.0, 
      "deltax": 0.0, 
      "deltay": 0.0, 
      "sizex": 150.0, 
      "sizey": 850.0, 
      "drill_x": 0.0, 
      "layer_mask": "00888000", 
      "shape": "rectangle", 
      "net_number": "0", 
      "drill_y": 0.0, 
      "posy": -1300.0, 
      "posx": -3325.0, 
      "shape_code": "R", 
      "type": "SMD", 
      "drill_shape": "circle", 
      "orientation": 0
    }, 
    {
      "net_name": "", 
      "angle": 0.0, 
      "name": "73", 
      "drill_diam": 0.0, 
      "deltax": 0.0, 
      "deltay": 0.0, 
      "sizex": 150.0, 
      "sizey": 850.0, 
      "drill_x": 0.0, 
      "layer_mask": "00888000", 
      "shape": "rectangle", 
      "net_number": "0", 
      "drill_y": 0.0, 
      "posy": 1300.0, 
      "posx": -3575.0, 
      "shape_code": "R", 
      "type": "SMD", 
      "drill_shape": "circle", 
      "orientation": 0
    }, 
    {
      "net_name": "", 
      "angle": 0.0, 
      "name": "74", 
      "drill_diam": 0.0, 
      "deltax": 0.0, 
      "deltay": 0.0, 
      "sizex": 150.0, 
      "sizey": 850.0, 
      "drill_x": 0.0, 
      "layer_mask": "00888000", 
      "shape": "rectangle", 
      "net_number": "0", 
      "drill_y": 0.0, 
      "posy": -1300.0, 
      "posx": -3575.0, 
      "shape_code": "R", 
      "type": "SMD", 
      "drill_shape": "circle", 
      "orientation": 0
    }, 
    {
      "net_name": "", 
      "angle": 0.0, 
      "name": "75", 
      "drill_diam": 0.0, 
      "deltax": 0.0, 
      "deltay": 0.0, 
      "sizex": 150.0, 
      "sizey": 850.0, 
      "drill_x": 0.0, 
      "layer_mask": "00888000", 
      "shape": "rectangle", 
      "net_number": "0", 
      "drill_y": 0.0, 
      "posy": 1300.0, 
      "posx": -3825.0, 
      "shape_code": "R", 
      "type": "SMD", 
      "drill_shape": "circle", 
      "orientation": 0
    }, 
    {
      "net_name": "", 
      "angle": 0.0, 
      "name": "76", 
      "drill_diam": 0.0, 
      "deltax": 0.0, 
      "deltay": 0.0, 
      "sizex": 150.0, 
      "sizey": 850.0, 
      "drill_x": 0.0, 
      "layer_mask": "00888000", 
      "shape": "rectangle", 
      "net_number": "0", 
      "drill_y": 0.0, 
      "posy": -1300.0, 
      "posx": -3825.0, 
      "shape_code": "R", 
      "type": "SMD", 
      "drill_shape": "circle", 
      "orientation": 0
    }, 
    {
      "net_name": "", 
      "angle": 0.0, 
      "name": "77", 
      "drill_diam": 0.0, 
      "deltax": 0.0, 
      "deltay": 0.0, 
      "sizex": 150.0, 
      "sizey": 850.0, 
      "drill_x": 0.0, 
      "layer_mask": "00888000", 
      "shape": "rectangle", 
      "net_number": "0", 
      "drill_y": 0.0, 
      "posy": 1300.0, 
      "posx": -4075.0, 
      "shape_code": "R", 
      "type": "SMD", 
      "drill_shape": "circle", 
      "orientation": 0
    }, 
    {
      "net_name": "", 
      "angle": 0.0, 
      "name": "78", 
      "drill_diam": 0.0, 
      "deltax": 0.0, 
      "deltay": 0.0, 
      "sizex": 150.0, 
      "sizey": 850.0, 
      "drill_x": 0.0, 
      "layer_mask": "00888000", 
      "shape": "rectangle", 
      "net_number": "0", 
      "drill_y": 0.0, 
      "posy": -1300.0, 
      "posx": -4075.0, 
      "shape_code": "R", 
      "type": "SMD", 
      "drill_shape": "circle", 
      "orientation": 0
    }, 
    {
      "net_name": "", 
      "angle": 0.0, 
      "name": "79", 
      "drill_diam": 0.0, 
      "deltax": 0.0, 
      "deltay": 0.0, 
      "sizex": 150.0, 
      "sizey": 850.0, 
      "drill_x": 0.0, 
      "layer_mask": "00888000", 
      "shape": "rectangle", 
      "net_number": "0", 
      "drill_y": 0.0, 
      "posy": 1300.0, 
      "posx": -4325.0, 
      "shape_code": "R", 
      "type": "SMD", 
      "drill_shape": "circle", 
      "orientation": 0
    }, 
    {
      "net_name": "", 
      "angle": 0.0, 
      "name": "80", 
      "drill_diam": 0.0, 
      "deltax": 0.0, 
      "deltay": 0.0, 
      "sizex": 150.0, 
      "sizey": 850.0, 
      "drill_x": 0.0, 
      "layer_mask": "00888000", 
      "shape": "rectangle", 
      "net_number": "0", 
      "drill_y": 0.0, 
      "posy": -1300.0, 
      "posx": -4325.0, 
      "shape_code": "R", 
      "type": "SMD", 
      "drill_shape": "circle", 
      "orientation": 0
    }, 
    {
      "net_name": "", 
      "angle": 0.0, 
      "name": "81", 
      "drill_diam": 0.0, 
      "deltax": 0.0, 
      "deltay": 0.0, 
      "sizex": 150.0, 
      "sizey": 850.0, 
      "drill_x": 0.0, 
      "layer_mask": "00888000", 
      "shape": "rectangle", 
      "net_number": "0", 
      "drill_y": 0.0, 
      "posy": 1300.0, 
      "posx": -4575.0, 
      "shape_code": "R", 
      "type": "SMD", 
      "drill_shape": "circle", 
      "orientation": 0
    }, 
    {
      "net_name": "", 
      "angle": 0.0, 
      "name": "82", 
      "drill_diam": 0.0, 
      "deltax": 0.0, 
      "deltay": 0.0, 
      "sizex": 150.0, 
      "sizey": 850.0, 
      "drill_x": 0.0, 
      "layer_mask": "00888000", 
      "shape": "rectangle", 
      "net_number": "0", 
      "drill_y": 0.0, 
      "posy": -1300.0, 
      "posx": -4575.0, 
      "shape_code": "R", 
      "type": "SMD", 
      "drill_shape": "circle", 
      "orientation": 0
    }, 
    {
      "net_name": "", 
      "angle": 0.0, 
      "name": "83", 
      "drill_diam": 0.0, 
      "deltax": 0.0, 
      "deltay": 0.0, 
      "sizex": 150.0, 
      "sizey": 850.0, 
      "drill_x": 0.0, 
      "layer_mask": "00888000", 
      "shape": "rectangle", 
      "net_number": "0", 
      "drill_y": 0.0, 
      "posy": 1300.0, 
      "posx": -4825.0, 
      "shape_code": "R", 
      "type": "SMD", 
      "drill_shape": "circle", 
      "orientation": 0
    }, 
    {
      "net_name": "", 
      "angle": 0.0, 
      "name": "84", 
      "drill_diam": 0.0, 
      "deltax": 0.0, 
      "deltay": 0.0, 
      "sizex": 150.0, 
      "sizey": 850.0, 
      "drill_x": 0.0, 
      "layer_mask": "00888000", 
      "shape": "rectangle", 
      "net_number": "0", 
      "drill_y": 0.0, 
      "posy": -1300.0, 
      "posx": -4825.0, 
      "shape_code": "R", 
      "type": "SMD", 
      "drill_shape": "circle", 
      "orientation": 0
    }, 
    {
      "net_name": "", 
      "angle": 0.0, 
      "name": "85", 
      "drill_diam": 0.0, 
      "deltax": 0.0, 
      "deltay": 0.0, 
      "sizex": 150.0, 
      "sizey": 850.0, 
      "drill_x": 0.0, 
      "layer_mask": "00888000", 
      "shape": "rectangle", 
      "net_number": "0", 
      "drill_y": 0.0, 
      "posy": 1300.0, 
      "posx": -5075.0, 
      "shape_code": "R", 
      "type": "SMD", 
      "drill_shape": "circle", 
      "orientation": 0
    }, 
    {
      "net_name": "", 
      "angle": 0.0, 
      "name": "86", 
      "drill_diam": 0.0, 
      "deltax": 0.0, 
      "deltay": 0.0, 
      "sizex": 150.0, 
      "sizey": 850.0, 
      "drill_x": 0.0, 
      "layer_mask": "00888000", 
      "shape": "rectangle", 
      "net_number": "0", 
      "drill_y": 0.0, 
      "posy": -1300.0, 
      "posx": -5075.0, 
      "shape_code": "R", 
      "type": "SMD", 
      "drill_shape": "circle", 
      "orientation": 0
    }, 
    {
      "net_name": "", 
      "angle": 0.0, 
      "name": "87", 
      "drill_diam": 0.0, 
      "deltax": 0.0, 
      "deltay": 0.0, 
      "sizex": 150.0, 
      "sizey": 850.0, 
      "drill_x": 0.0, 
      "layer_mask": "00888000", 
      "shape": "rectangle", 
      "net_number": "0", 
      "drill_y": 0.0, 
      "posy": 1300.0, 
      "posx": -5325.0, 
      "shape_code": "R", 
      "type": "SMD", 
      "drill_shape": "circle", 
      "orientation": 0
    }, 
    {
      "net_name": "", 
      "angle": 0.0, 
      "name": "88", 
      "drill_diam": 0.0, 
      "deltax": 0.0, 
      "deltay": 0.0, 
      "sizex": 150.0, 
      "sizey": 850.0, 
      "drill_x": 0.0, 
      "layer_mask": "00888000", 
      "shape": "rectangle", 
      "net_number": "0", 
      "drill_y": 0.0, 
      "posy": -1300.0, 
      "posx": -5325.0, 
      "shape_code": "R", 
      "type": "SMD", 
      "drill_shape": "circle", 
      "orientation": 0
    }, 
    {
      "net_name": "", 
      "angle": 0.0, 
      "name": "89", 
      "drill_diam": 0.0, 
      "deltax": 0.0, 
      "deltay": 0.0, 
      "sizex": 150.0, 
      "sizey": 850.0, 
      "drill_x": 0.0, 
      "layer_mask": "00888000", 
      "shape": "rectangle", 
      "net_number": "0", 
      "drill_y": 0.0, 
      "posy": 1300.0, 
      "posx": -5575.0, 
      "shape_code": "R", 
      "type": "SMD", 
      "drill_shape": "circle", 
      "orientation": 0
    }, 
    {
      "net_name": "", 
      "angle": 0.0, 
      "name": "90", 
      "drill_diam": 0.0, 
      "deltax": 0.0, 
      "deltay": 0.0, 
      "sizex": 150.0, 
      "sizey": 850.0, 
      "drill_x": 0.0, 
      "layer_mask": "00888000", 
      "shape": "rectangle", 
      "net_number": "0", 
      "drill_y": 0.0, 
      "posy": -1300.0, 
      "posx": -5575.0, 
      "shape_code": "R", 
      "type": "SMD", 
      "drill_shape": "circle", 
      "orientation": 0
    }, 
    {
      "net_name": "", 
      "angle": 0.0, 
      "name": "91", 
      "drill_diam": 0.0, 
      "deltax": 0.0, 
      "deltay": 0.0, 
      "sizex": 150.0, 
      "sizey": 850.0, 
      "drill_x": 0.0, 
      "layer_mask": "00888000", 
      "shape": "rectangle", 
      "net_number": "0", 
      "drill_y": 0.0, 
      "posy": 1300.0, 
      "posx": -5825.0, 
      "shape_code": "R", 
      "type": "SMD", 
      "drill_shape": "circle", 
      "orientation": 0
    }, 
    {
      "net_name": "", 
      "angle": 0.0, 
      "name": "92", 
      "drill_diam": 0.0, 
      "deltax": 0.0, 
      "deltay": 0.0, 
      "sizex": 150.0, 
      "sizey": 850.0, 
      "drill_x": 0.0, 
      "layer_mask": "00888000", 
      "shape": "rectangle", 
      "net_number": "0", 
      "drill_y": 0.0, 
      "posy": -1300.0, 
      "posx": -5825.0, 
      "shape_code": "R", 
      "type": "SMD", 
      "drill_shape": "circle", 
      "orientation": 0
    }, 
    {
      "net_name": "", 
      "angle": 0.0, 
      "name": "93", 
      "drill_diam": 0.0, 
      "deltax": 0.0, 
      "deltay": 0.0, 
      "sizex": 150.0, 
      "sizey": 850.0, 
      "drill_x": 0.0, 
      "layer_mask": "00888000", 
      "shape": "rectangle", 
      "net_number": "0", 
      "drill_y": 0.0, 
      "posy": 1300.0, 
      "posx": -6075.0, 
      "shape_code": "R", 
      "type": "SMD", 
      "drill_shape": "circle", 
      "orientation": 0
    }, 
    {
      "net_name": "", 
      "angle": 0.0, 
      "name": "94", 
      "drill_diam": 0.0, 
      "deltax": 0.0, 
      "deltay": 0.0, 
      "sizex": 150.0, 
      "sizey": 850.0, 
      "drill_x": 0.0, 
      "layer_mask": "00888000", 
      "shape": "rectangle", 
      "net_number": "0", 
      "drill_y": 0.0, 
      "posy": -1300.0, 
      "posx": -6075.0, 
      "shape_code": "R", 
      "type": "SMD", 
      "drill_shape": "circle", 
      "orientation": 0
    }, 
    {
      "net_name": "", 
      "angle": 0.0, 
      "name": "95", 
      "drill_diam": 0.0, 
      "deltax": 0.0, 
      "deltay": 0.0, 
      "sizex": 150.0, 
      "sizey": 850.0, 
      "drill_x": 0.0, 
      "layer_mask": "00888000", 
      "shape": "rectangle", 
      "net_number": "0", 
      "drill_y": 0.0, 
      "posy": 1300.0, 
      "posx": -6325.0, 
      "shape_code": "R", 
      "type": "SMD", 
      "drill_shape": "circle", 
      "orientation": 0
    }, 
    {
      "net_name": "", 
      "angle": 0.0, 
      "name": "96", 
      "drill_diam": 0.0, 
      "deltax": 0.0, 
      "deltay": 0.0, 
      "sizex": 150.0, 
      "sizey": 850.0, 
      "drill_x": 0.0, 
      "layer_mask": "00888000", 
      "shape": "rectangle", 
      "net_number": "0", 
      "drill_y": 0.0, 
      "posy": -1300.0, 
      "posx": -6325.0, 
      "shape_code": "R", 
      "type": "SMD", 
      "drill_shape": "circle", 
      "orientation": 0
    }, 
    {
      "net_name": "", 
      "angle": 0.0, 
      "name": "97", 
      "drill_diam": 0.0, 
      "deltax": 0.0, 
      "deltay": 0.0, 
      "sizex": 150.0, 
      "sizey": 850.0, 
      "drill_x": 0.0, 
      "layer_mask": "00888000", 
      "shape": "rectangle", 
      "net_number": "0", 
      "drill_y": 0.0, 
      "posy": 1300.0, 
      "posx": -6575.0, 
      "shape_code": "R", 
      "type": "SMD", 
      "drill_shape": "circle", 
      "orientation": 0
    }, 
    {
      "net_name": "", 
      "angle": 0.0, 
      "name": "98", 
      "drill_diam": 0.0, 
      "deltax": 0.0, 
      "deltay": 0.0, 
      "sizex": 150.0, 
      "sizey": 850.0, 
      "drill_x": 0.0, 
      "layer_mask": "00888000", 
      "shape": "rectangle", 
      "net_number": "0", 
      "drill_y": 0.0, 
      "posy": -1300.0, 
      "posx": -6575.0, 
      "shape_code": "R", 
      "type": "SMD", 
      "drill_shape": "circle", 
      "orientation": 0
    }, 
    {
      "net_name": "", 
      "angle": 0.0, 
      "name": "99", 
      "drill_diam": 0.0, 
      "deltax": 0.0, 
      "deltay": 0.0, 
      "sizex": 150.0, 
      "sizey": 850.0, 
      "drill_x": 0.0, 
      "layer_mask": "00888000", 
      "shape": "rectangle", 
      "net_number": "0", 
      "drill_y": 0.0, 
      "posy": 1300.0, 
      "posx": -6825.0, 
      "shape_code": "R", 
      "type": "SMD", 
      "drill_shape": "circle", 
      "orientation": 0
    }, 
    {
      "net_name": "", 
      "angle": 0.0, 
      "name": "100", 
      "drill_diam": 0.0, 
      "deltax": 0.0, 
      "deltay": 0.0, 
      "sizex": 150.0, 
      "sizey": 850.0, 
      "drill_x": 0.0, 
      "layer_mask": "00888000", 
      "shape": "rectangle", 
      "net_number": "0", 
      "drill_y": 0.0, 
      "posy": -1300.0, 
      "posx": -6825.0, 
      "shape_code": "R", 
      "type": "SMD", 
      "drill_shape": "circle", 
      "orientation": 0
    }, 
    {
      "net_name": "", 
      "angle": 0.0, 
      "name": "101", 
      "drill_diam": 0.0, 
      "deltax": 0.0, 
      "deltay": 0.0, 
      "sizex": 150.0, 
      "sizey": 850.0, 
      "drill_x": 0.0, 
      "layer_mask": "00888000", 
      "shape": "rectangle", 
      "net_number": "0", 
      "drill_y": 0.0, 
      "posy": 1300.0, 
      "posx": -7075.0, 
      "shape_code": "R", 
      "type": "SMD", 
      "drill_shape": "circle", 
      "orientation": 0
    }, 
    {
      "net_name": "", 
      "angle": 0.0, 
      "name": "102", 
      "drill_diam": 0.0, 
      "deltax": 0.0, 
      "deltay": 0.0, 
      "sizex": 150.0, 
      "sizey": 850.0, 
      "drill_x": 0.0, 
      "layer_mask": "00888000", 
      "shape": "rectangle", 
      "net_number": "0", 
      "drill_y": 0.0, 
      "posy": -1300.0, 
      "posx": -7075.0, 
      "shape_code": "R", 
      "type": "SMD", 
      "drill_shape": "circle", 
      "orientation": 0
    }, 
    {
      "net_name": "", 
      "angle": 0.0, 
      "name": "103", 
      "drill_diam": 0.0, 
      "deltax": 0.0, 
      "deltay": 0.0, 
      "sizex": 150.0, 
      "sizey": 850.0, 
      "drill_x": 0.0, 
      "layer_mask": "00888000", 
      "shape": "rectangle", 
      "net_number": "0", 
      "drill_y": 0.0, 
      "posy": 1300.0, 
      "posx": -7325.0, 
      "shape_code": "R", 
      "type": "SMD", 
      "drill_shape": "circle", 
      "orientation": 0
    }, 
    {
      "net_name": "", 
      "angle": 0.0, 
      "name": "104", 
      "drill_diam": 0.0, 
      "deltax": 0.0, 
      "deltay": 0.0, 
      "sizex": 150.0, 
      "sizey": 850.0, 
      "drill_x": 0.0, 
      "layer_mask": "00888000", 
      "shape": "rectangle", 
      "net_number": "0", 
      "drill_y": 0.0, 
      "posy": -1300.0, 
      "posx": -7325.0, 
      "shape_code": "R", 
      "type": "SMD", 
      "drill_shape": "circle", 
      "orientation": 0
    }, 
    {
      "net_name": "", 
      "angle": 0.0, 
      "name": "106", 
      "drill_diam": 0.0, 
      "deltax": 0.0, 
      "deltay": 0.0, 
      "sizex": 7100.0, 
      "sizey": 200.0, 
      "drill_x": 0.0, 
      "layer_mask": "00888000", 
      "shape": "rectangle", 
      "net_number": "0", 
      "drill_y": 0.0, 
      "posy": 0.0, 
      "posx": -4200.0, 
      "shape_code": "R", 
      "type": "SMD", 
      "drill_shape": "circle", 
      "orientation": 0
    }, 
    {
      "net_name": "", 
      "angle": 0.0, 
      "name": "105", 
      "drill_diam": 0.0, 
      "deltax": 0.0, 
      "deltay": 0.0, 
      "sizex": 7100.0, 
      "sizey": 200.0, 
      "drill_x": 0.0, 
      "layer_mask": "00888000", 
      "shape": "rectangle", 
      "net_number": "0", 
      "drill_y": 0.0, 
      "posy": 0.0, 
      "posx": 4200.0, 
      "shape_code": "R", 
      "type": "SMD", 
      "drill_shape": "circle", 
      "orientation": 0
    }, 
    {
      "net_name": "", 
      "angle": 0.0, 
      "name": "", 
      "drill_diam": 500.0, 
      "deltax": 0.0, 
      "deltay": 0.0, 
      "sizex": 600.0, 
      "sizey": 600.0, 
      "drill_x": 0.0, 
      "layer_mask": "00E0FFFF", 
      "shape": "circle", 
      "net_number": "0", 
      "drill_y": 0.0, 
      "posy": 800.0, 
      "posx": -8250.0, 
      "shape_code": "C", 
      "type": "STD", 
      "drill_shape": "circle", 
      "orientation": 0
    }, 
    {
      "net_name": "", 
      "angle": 0.0, 
      "name": "", 
      "drill_diam": 500.0, 
      "deltax": 0.0, 
      "deltay": 0.0, 
      "sizex": 600.0, 
      "sizey": 600.0, 
      "drill_x": 0.0, 
      "layer_mask": "00E0FFFF", 
      "shape": "circle", 
      "net_number": "0", 
      "drill_y": 0.0, 
      "posy": 800.0, 
      "posx": 8250.0, 
      "shape_code": "C", 
      "type": "STD", 
      "drill_shape": "circle", 
      "orientation": 0
    }
  ], 
  "timestamp": "4E4E7320", 
  "units": "mm", 
  "x": 0.0, 
  "rotation_cost_90": "0", 
  "angle": 0.0, 
  "orientation": "0"
}