{
  "library_name": "JOYSTICK_MINI", 
  "layer": "15", 
  "attribute1": "00000000", 
  "art": [
    {
      "line_width": 80.0, 
      "startx": 1043.0, 
      "starty": 1377.0, 
      "endy": 1377.0, 
      "endx": -1043.0, 
      "layer": "21", 
      "shape": "segment"
    }, 
    {
      "line_width": 80.0, 
      "startx": -1043.0, 
      "starty": 1377.0, 
      "endy": 984.0, 
      "endx": -1437.0, 
      "layer": "21", 
      "shape": "segment"
    }, 
    {
      "line_width": 80.0, 
      "startx": -1437.0, 
      "starty": 984.0, 
      "endy": -984.0, 
      "endx": -1437.0, 
      "layer": "21", 
      "shape": "segment"
    }, 
    {
      "line_width": 80.0, 
      "startx": -1437.0, 
      "starty": -984.0, 
      "endy": -1377.0, 
      "endx": -1043.0, 
      "layer": "21", 
      "shape": "segment"
    }, 
    {
      "line_width": 80.0, 
      "startx": -1043.0, 
      "starty": -1377.0, 
      "endy": -1377.0, 
      "endx": -393.0, 
      "layer": "21", 
      "shape": "segment"
    }, 
    {
      "line_width": 80.0, 
      "startx": 393.0, 
      "starty": -1377.0, 
      "endy": -1377.0, 
      "endx": 1043.0, 
      "layer": "21", 
      "shape": "segment"
    }, 
    {
      "line_width": 80.0, 
      "startx": 1043.0, 
      "starty": -1377.0, 
      "endy": -984.0, 
      "endx": 1437.0, 
      "layer": "21", 
      "shape": "segment"
    }, 
    {
      "line_width": 80.0, 
      "startx": 1437.0, 
      "starty": -984.0, 
      "endy": 984.0, 
      "endx": 1437.0, 
      "layer": "21", 
      "shape": "segment"
    }, 
    {
      "line_width": 80.0, 
      "startx": 1437.0, 
      "starty": 984.0, 
      "endy": 1377.0, 
      "endx": 1043.0, 
      "layer": "21", 
      "shape": "segment"
    }, 
    {
      "line_width": 80.0, 
      "startx": -411.0, 
      "starty": 139.0, 
      "endy": 411.0, 
      "endx": -139.0, 
      "layer": "21", 
      "shape": "segment"
    }, 
    {
      "line_width": 80.0, 
      "layer": "21", 
      "angle": -1.5707963267948966, 
      "start_angle": 2.356194490192345, 
      "shape": "arc", 
      "r": 196.5756851698602, 
      "start_x": "-139", 
      "start_y": "411", 
      "y": "272", 
      "x": "0"
    }, 
    {
      "line_width": 80.0, 
      "startx": 139.0, 
      "starty": 411.0, 
      "endy": 139.0, 
      "endx": 411.0, 
      "layer": "21", 
      "shape": "segment"
    }, 
    {
      "line_width": 80.0, 
      "layer": "21", 
      "angle": -1.5707963267948966, 
      "start_angle": 0.7853981633974483, 
      "shape": "arc", 
      "r": 196.5756851698602, 
      "start_x": "411", 
      "start_y": "139", 
      "y": "0", 
      "x": "272"
    }, 
    {
      "line_width": 80.0, 
      "startx": 411.0, 
      "starty": -139.0, 
      "endy": -411.0, 
      "endx": 139.0, 
      "layer": "21", 
      "shape": "segment"
    }, 
    {
      "line_width": 80.0, 
      "layer": "21", 
      "angle": -1.5707963267948966, 
      "start_angle": -0.7853981633974483, 
      "shape": "arc", 
      "r": 196.5756851698602, 
      "start_x": "139", 
      "start_y": "-411", 
      "y": "-272", 
      "x": "0"
    }, 
    {
      "line_width": 80.0, 
      "startx": -139.0, 
      "starty": -411.0, 
      "endy": -139.0, 
      "endx": -411.0, 
      "layer": "21", 
      "shape": "segment"
    }, 
    {
      "line_width": 80.0, 
      "layer": "21", 
      "angle": -1.5707963267948966, 
      "start_angle": -2.356194490192345, 
      "shape": "arc", 
      "r": 196.5756851698602, 
      "start_x": "-411", 
      "start_y": "-139", 
      "y": "0", 
      "x": "-272"
    }, 
    {
      "line_width": 80.0, 
      "startx": 0.0, 
      "starty": -984.0, 
      "endy": -1377.0, 
      "endx": 393.0, 
      "layer": "21", 
      "shape": "segment"
    }, 
    {
      "line_width": 80.0, 
      "startx": 0.0, 
      "starty": -984.0, 
      "endy": -1377.0, 
      "endx": -393.0, 
      "layer": "21", 
      "shape": "segment"
    }, 
    {
      "line_width": 80.0, 
      "startx": -511.0, 
      "starty": -511.0, 
      "endy": -866.0, 
      "endx": -866.0, 
      "layer": "21", 
      "shape": "segment"
    }, 
    {
      "line_width": 80.0, 
      "startx": -866.0, 
      "starty": -866.0, 
      "endy": -866.0, 
      "endx": -629.0, 
      "layer": "21", 
      "shape": "segment"
    }, 
    {
      "line_width": 80.0, 
      "startx": -866.0, 
      "starty": -866.0, 
      "endy": -629.0, 
      "endx": -866.0, 
      "layer": "21", 
      "shape": "segment"
    }, 
    {
      "line_width": 80.0, 
      "startx": -393.0, 
      "starty": -1377.0, 
      "endy": -1377.0, 
      "endx": 393.0, 
      "layer": "21", 
      "shape": "segment"
    }, 
    {
      "line_width": 80.0, 
      "startx": 1043.0, 
      "starty": 1377.0, 
      "endy": 1377.0, 
      "endx": -1043.0, 
      "layer": "25", 
      "shape": "segment"
    }, 
    {
      "line_width": 80.0, 
      "startx": -1043.0, 
      "starty": 1377.0, 
      "endy": 984.0, 
      "endx": -1437.0, 
      "layer": "25", 
      "shape": "segment"
    }, 
    {
      "line_width": 80.0, 
      "startx": -1437.0, 
      "starty": 984.0, 
      "endy": -984.0, 
      "endx": -1437.0, 
      "layer": "25", 
      "shape": "segment"
    }, 
    {
      "line_width": 80.0, 
      "startx": -1437.0, 
      "starty": -984.0, 
      "endy": -1377.0, 
      "endx": -1043.0, 
      "layer": "25", 
      "shape": "segment"
    }, 
    {
      "line_width": 80.0, 
      "startx": -1043.0, 
      "starty": -1377.0, 
      "endy": -1377.0, 
      "endx": -393.0, 
      "layer": "25", 
      "shape": "segment"
    }, 
    {
      "line_width": 80.0, 
      "startx": 393.0, 
      "starty": -1377.0, 
      "endy": -1377.0, 
      "endx": 1043.0, 
      "layer": "25", 
      "shape": "segment"
    }, 
    {
      "line_width": 80.0, 
      "startx": 1043.0, 
      "starty": -1377.0, 
      "endy": -984.0, 
      "endx": 1437.0, 
      "layer": "25", 
      "shape": "segment"
    }, 
    {
      "line_width": 80.0, 
      "startx": 1437.0, 
      "starty": -984.0, 
      "endy": 984.0, 
      "endx": 1437.0, 
      "layer": "25", 
      "shape": "segment"
    }, 
    {
      "line_width": 80.0, 
      "startx": 1437.0, 
      "starty": 984.0, 
      "endy": 1377.0, 
      "endx": 1043.0, 
      "layer": "25", 
      "shape": "segment"
    }, 
    {
      "line_width": 80.0, 
      "startx": -411.0, 
      "starty": 139.0, 
      "endy": 411.0, 
      "endx": -139.0, 
      "layer": "25", 
      "shape": "segment"
    }, 
    {
      "line_width": 80.0, 
      "layer": "25", 
      "angle": -1.5707963267948966, 
      "start_angle": 2.356194490192345, 
      "shape": "arc", 
      "r": 196.5756851698602, 
      "start_x": "-139", 
      "start_y": "411", 
      "y": "272", 
      "x": "0"
    }, 
    {
      "line_width": 80.0, 
      "startx": 139.0, 
      "starty": 411.0, 
      "endy": 139.0, 
      "endx": 411.0, 
      "layer": "25", 
      "shape": "segment"
    }, 
    {
      "line_width": 80.0, 
      "layer": "25", 
      "angle": -1.5707963267948966, 
      "start_angle": 0.7853981633974483, 
      "shape": "arc", 
      "r": 196.5756851698602, 
      "start_x": "411", 
      "start_y": "139", 
      "y": "0", 
      "x": "272"
    }, 
    {
      "line_width": 80.0, 
      "startx": 411.0, 
      "starty": -139.0, 
      "endy": -411.0, 
      "endx": 139.0, 
      "layer": "25", 
      "shape": "segment"
    }, 
    {
      "line_width": 80.0, 
      "layer": "25", 
      "angle": -1.5707963267948966, 
      "start_angle": -0.7853981633974483, 
      "shape": "arc", 
      "r": 196.5756851698602, 
      "start_x": "139", 
      "start_y": "-411", 
      "y": "-272", 
      "x": "0"
    }, 
    {
      "line_width": 80.0, 
      "startx": -139.0, 
      "starty": -411.0, 
      "endy": -139.0, 
      "endx": -411.0, 
      "layer": "25", 
      "shape": "segment"
    }, 
    {
      "line_width": 80.0, 
      "layer": "25", 
      "angle": -1.5707963267948966, 
      "start_angle": -2.356194490192345, 
      "shape": "arc", 
      "r": 196.5756851698602, 
      "start_x": "-411", 
      "start_y": "-139", 
      "y": "0", 
      "x": "-272"
    }, 
    {
      "line_width": 80.0, 
      "startx": 0.0, 
      "starty": -984.0, 
      "endy": -1377.0, 
      "endx": 393.0, 
      "layer": "25", 
      "shape": "segment"
    }, 
    {
      "line_width": 80.0, 
      "startx": 0.0, 
      "starty": -984.0, 
      "endy": -1377.0, 
      "endx": -393.0, 
      "layer": "25", 
      "shape": "segment"
    }, 
    {
      "line_width": 80.0, 
      "startx": -511.0, 
      "starty": -511.0, 
      "endy": -866.0, 
      "endx": -866.0, 
      "layer": "25", 
      "shape": "segment"
    }, 
    {
      "line_width": 80.0, 
      "startx": -866.0, 
      "starty": -866.0, 
      "endy": -866.0, 
      "endx": -629.0, 
      "layer": "25", 
      "shape": "segment"
    }, 
    {
      "line_width": 80.0, 
      "startx": -866.0, 
      "starty": -866.0, 
      "endy": -629.0, 
      "endx": -866.0, 
      "layer": "25", 
      "shape": "segment"
    }, 
    {
      "line_width": 80.0, 
      "startx": -393.0, 
      "starty": -1377.0, 
      "endy": -1377.0, 
      "endx": 393.0, 
      "layer": "25", 
      "shape": "segment"
    }, 
    {
      "line_width": 80.0, 
      "layer": "21", 
      "shape": "circle", 
      "r": 590.0, 
      "y": 0.0, 
      "x": 0.0
    }, 
    {
      "line_width": 80.0, 
      "layer": "25", 
      "shape": "circle", 
      "r": 590.0, 
      "y": 0.0, 
      "x": 0.0
    }
  ], 
  "name": "JOYSTICK_MINI", 
  "text": [
    {
      "layer": "25", 
      "angle": 0.0, 
      "misc": " \"ref**\"", 
      "sizex": 0.0, 
      "number": "0", 
      "sizey": 0.0, 
      "visible": false, 
      "flag": "N", 
      "text": "ref**", 
      "y": 0.0, 
      "x": 0.0, 
      "rotation": "0", 
      "penwidth": 0.0
    }, 
    {
      "layer": "26", 
      "angle": 0.0, 
      "misc": " \"val**\"", 
      "sizex": 0.0, 
      "number": "1", 
      "sizey": 0.0, 
      "visible": false, 
      "flag": "N", 
      "text": "val**", 
      "y": 0.0, 
      "x": 0.0, 
      "rotation": "0", 
      "penwidth": 0.0
    }, 
    {
      "layer": "26", 
      "angle": 0.0, 
      "misc": " \">Name\"", 
      "sizex": 160.0, 
      "number": "2", 
      "sizey": 160.0, 
      "visible": true, 
      "flag": "N", 
      "text": ">Name", 
      "y": -1416.0, 
      "x": -664.0, 
      "rotation": "0", 
      "penwidth": 12.0
    }, 
    {
      "layer": "26", 
      "angle": 0.0, 
      "misc": " \">Value\"", 
      "sizex": 160.0, 
      "number": "3", 
      "sizey": 160.0, 
      "visible": true, 
      "flag": "N", 
      "text": ">Value", 
      "y": 1733.0, 
      "x": -504.0, 
      "rotation": "0", 
      "penwidth": 12.0
    }, 
    {
      "layer": "21", 
      "angle": 0.7853981633974483, 
      "misc": " \"UP\"", 
      "sizex": 320.0, 
      "number": "4", 
      "sizey": 320.0, 
      "visible": true, 
      "flag": "N", 
      "text": "UP", 
      "y": -748.0, 
      "x": -1141.0, 
      "rotation": "450", 
      "penwidth": 64.0
    }, 
    {
      "layer": "25", 
      "angle": 0.7853981633974483, 
      "misc": " \"UP\"", 
      "sizex": 320.0, 
      "number": "5", 
      "sizey": 320.0, 
      "visible": true, 
      "flag": "N", 
      "text": "UP", 
      "y": -748.0, 
      "x": -1141.0, 
      "rotation": "450", 
      "penwidth": 64.0
    }
  ], 
  "timestamp_op": "00000000", 
  "rotation_cost_180": "0", 
  "attribute2": "~~", 
  "y": 0.0, 
  "rotation_cost_misc": "0", 
  "pad": [
    {
      "angle": 0.0, 
      "name": "Hole", 
      "drill_diam": 295.0, 
      "deltax": 0.0, 
      "deltay": 0.0, 
      "sizex": 295.0, 
      "sizey": 295.0, 
      "drill_x": 0.0, 
      "layer_mask": "00E0FFFF", 
      "shape": "circle", 
      "drill_y": 0.0, 
      "posy": -748.0, 
      "posx": 0.0, 
      "shape_code": "C", 
      "type": "HOLE", 
      "drill_shape": "circle", 
      "orientation": 0
    }, 
    {
      "angle": 0.0, 
      "name": "Hole", 
      "drill_diam": 413.0, 
      "deltax": 0.0, 
      "deltay": 0.0, 
      "sizex": 413.0, 
      "sizey": 413.0, 
      "drill_x": 0.0, 
      "layer_mask": "00E0FFFF", 
      "shape": "circle", 
      "drill_y": 0.0, 
      "posy": 748.0, 
      "posx": 0.0, 
      "shape_code": "C", 
      "type": "HOLE", 
      "drill_shape": "circle", 
      "orientation": 0
    }, 
    {
      "angle": 0.0, 
      "name": "A", 
      "drill_diam": 0.0, 
      "deltax": 0.0, 
      "deltay": 0.0, 
      "sizex": 728.0, 
      "sizey": 433.0, 
      "drill_x": 0.0, 
      "layer_mask": "00888000", 
      "shape": "rectangle", 
      "drill_y": 0.0, 
      "posy": -551.0, 
      "posx": -1309.0, 
      "shape_code": "R", 
      "type": "SMD", 
      "drill_shape": "circle", 
      "orientation": 0
    }, 
    {
      "angle": 0.0, 
      "name": "B", 
      "drill_diam": 0.0, 
      "deltax": 0.0, 
      "deltay": 0.0, 
      "sizex": 728.0, 
      "sizey": 433.0, 
      "drill_x": 0.0, 
      "layer_mask": "00888000", 
      "shape": "rectangle", 
      "drill_y": 0.0, 
      "posy": -551.0, 
      "posx": 1309.0, 
      "shape_code": "R", 
      "type": "SMD", 
      "drill_shape": "circle", 
      "orientation": 0
    }, 
    {
      "angle": 0.0, 
      "name": "C", 
      "drill_diam": 0.0, 
      "deltax": 0.0, 
      "deltay": 0.0, 
      "sizex": 728.0, 
      "sizey": 433.0, 
      "drill_x": 0.0, 
      "layer_mask": "00888000", 
      "shape": "rectangle", 
      "drill_y": 0.0, 
      "posy": 551.0, 
      "posx": -1309.0, 
      "shape_code": "R", 
      "type": "SMD", 
      "drill_shape": "circle", 
      "orientation": 0
    }, 
    {
      "angle": 0.0, 
      "name": "CTR", 
      "drill_diam": 0.0, 
      "deltax": 0.0, 
      "deltay": 0.0, 
      "sizex": 728.0, 
      "sizey": 433.0, 
      "drill_x": 0.0, 
      "layer_mask": "00888000", 
      "shape": "rectangle", 
      "drill_y": 0.0, 
      "posy": 0.0, 
      "posx": -1309.0, 
      "shape_code": "R", 
      "type": "SMD", 
      "drill_shape": "circle", 
      "orientation": 0
    }, 
    {
      "angle": 0.0, 
      "name": "D", 
      "drill_diam": 0.0, 
      "deltax": 0.0, 
      "deltay": 0.0, 
      "sizex": 728.0, 
      "sizey": 433.0, 
      "drill_x": 0.0, 
      "layer_mask": "00888000", 
      "shape": "rectangle", 
      "drill_y": 0.0, 
      "posy": 551.0, 
      "posx": 1309.0, 
      "shape_code": "R", 
      "type": "SMD", 
      "drill_shape": "circle", 
      "orientation": 0
    }, 
    {
      "angle": 0.0, 
      "name": "GND", 
      "drill_diam": 0.0, 
      "deltax": 0.0, 
      "deltay": 0.0, 
      "sizex": 728.0, 
      "sizey": 433.0, 
      "drill_x": 0.0, 
      "layer_mask": "00888000", 
      "shape": "rectangle", 
      "drill_y": 0.0, 
      "posy": 0.0, 
      "posx": 1309.0, 
      "shape_code": "R", 
      "type": "SMD", 
      "drill_shape": "circle", 
      "orientation": 0
    }, 
    {
      "angle": 0.0, 
      "name": "NC", 
      "drill_diam": 0.0, 
      "deltax": 0.0, 
      "deltay": 0.0, 
      "sizex": 748.0, 
      "sizey": 787.0, 
      "drill_x": 0.0, 
      "layer_mask": "00888000", 
      "shape": "rectangle", 
      "drill_y": 0.0, 
      "posy": -1625.0, 
      "posx": 0.0, 
      "shape_code": "R", 
      "type": "SMD", 
      "drill_shape": "circle", 
      "orientation": 0
    }, 
    {
      "angle": 0.0, 
      "name": "NC@0", 
      "drill_diam": 0.0, 
      "deltax": 0.0, 
      "deltay": 0.0, 
      "sizex": 748.0, 
      "sizey": 787.0, 
      "drill_x": 0.0, 
      "layer_mask": "00888000", 
      "shape": "rectangle", 
      "drill_y": 0.0, 
      "posy": 1625.0, 
      "posx": 0.0, 
      "shape_code": "R", 
      "type": "SMD", 
      "drill_shape": "circle", 
      "orientation": 0
    }
  ], 
  "timestamp": "00000000", 
  "units": "deci-mils", 
  "x": 0.0, 
  "rotation_cost_90": "0", 
  "angle": 0.0, 
  "orientation": "0"
}