{
  "art": [
    {
      "count": 2, 
      "line_width": "10", 
      "convert": "0", 
      "shape": "path", 
      "path": [
        [
          400.0, 
          900.0
        ], 
        [
          600.0, 
          900.0
        ]
      ], 
      "de_morgan_alternate_shape": "0", 
      "unit": "0", 
      "fill": "N"
    }, 
    {
      "count": 2, 
      "line_width": "10", 
      "convert": "0", 
      "shape": "path", 
      "path": [
        [
          600.0, 
          900.0
        ], 
        [
          600.0, 
          -700.0
        ]
      ], 
      "de_morgan_alternate_shape": "0", 
      "unit": "0", 
      "fill": "N"
    }, 
    {
      "count": 2, 
      "line_width": "10", 
      "convert": "0", 
      "shape": "path", 
      "path": [
        [
          600.0, 
          -700.0
        ], 
        [
          400.0, 
          -700.0
        ]
      ], 
      "de_morgan_alternate_shape": "0", 
      "unit": "0", 
      "fill": "N"
    }, 
    {
      "count": 2, 
      "line_width": "10", 
      "convert": "0", 
      "shape": "path", 
      "path": [
        [
          400.0, 
          -700.0
        ], 
        [
          400.0, 
          900.0
        ]
      ], 
      "de_morgan_alternate_shape": "0", 
      "unit": "0", 
      "fill": "N"
    }, 
    {
      "count": 2, 
      "line_width": "8", 
      "convert": "0", 
      "shape": "path", 
      "path": [
        [
          500.0, 
          800.0
        ], 
        [
          200.0, 
          800.0
        ]
      ], 
      "de_morgan_alternate_shape": "0", 
      "unit": "0", 
      "fill": "N"
    }, 
    {
      "count": 2, 
      "line_width": "8", 
      "convert": "0", 
      "shape": "path", 
      "path": [
        [
          200.0, 
          800.0
        ], 
        [
          200.0, 
          1000.0
        ]
      ], 
      "de_morgan_alternate_shape": "0", 
      "unit": "0", 
      "fill": "N"
    }, 
    {
      "count": 2, 
      "line_width": "8", 
      "convert": "0", 
      "shape": "path", 
      "path": [
        [
          200.0, 
          1000.0
        ], 
        [
          -100.0, 
          1000.0
        ]
      ], 
      "de_morgan_alternate_shape": "0", 
      "unit": "0", 
      "fill": "N"
    }, 
    {
      "line_width": 8, 
      "start_angle": 1.5707963267948966, 
      "end_angle": -1.5707963267948966, 
      "shape": "arc", 
      "r": 49.0, 
      "counterclockwise": true, 
      "y": 950.0, 
      "x": -100.0, 
      "de_morgan_alternate_shape": "0", 
      "unit": "0", 
      "fill": "N"
    }, 
    {
      "line_width": 8, 
      "start_angle": 1.5707963267948966, 
      "end_angle": -1.5707963267948966, 
      "shape": "arc", 
      "r": 49.0, 
      "counterclockwise": true, 
      "y": 850.0, 
      "x": -100.0, 
      "de_morgan_alternate_shape": "0", 
      "unit": "0", 
      "fill": "N"
    }, 
    {
      "line_width": 8, 
      "start_angle": 1.5707963267948966, 
      "end_angle": -1.5707963267948966, 
      "shape": "arc", 
      "r": 49.0, 
      "counterclockwise": true, 
      "y": 750.0, 
      "x": -100.0, 
      "de_morgan_alternate_shape": "0", 
      "unit": "0", 
      "fill": "N"
    }, 
    {
      "line_width": 8, 
      "start_angle": 1.5707963267948966, 
      "end_angle": -1.5707963267948966, 
      "shape": "arc", 
      "r": 50.0, 
      "counterclockwise": true, 
      "y": 650.0, 
      "x": -100.0, 
      "de_morgan_alternate_shape": "0", 
      "unit": "0", 
      "fill": "N"
    }, 
    {
      "line_width": 8, 
      "start_angle": 1.5707963267948966, 
      "end_angle": -1.5707963267948966, 
      "shape": "arc", 
      "r": 50.0, 
      "counterclockwise": true, 
      "y": 550.0, 
      "x": -100.0, 
      "de_morgan_alternate_shape": "0", 
      "unit": "0", 
      "fill": "N"
    }, 
    {
      "line_width": 8, 
      "start_angle": 1.5707963267948966, 
      "end_angle": -1.5707963267948966, 
      "shape": "arc", 
      "r": 49.0, 
      "counterclockwise": true, 
      "y": 450.0, 
      "x": -100.0, 
      "de_morgan_alternate_shape": "0", 
      "unit": "0", 
      "fill": "N"
    }, 
    {
      "count": 2, 
      "line_width": "8", 
      "convert": "0", 
      "shape": "path", 
      "path": [
        [
          -100.0, 
          400.0
        ], 
        [
          200.0, 
          400.0
        ]
      ], 
      "de_morgan_alternate_shape": "0", 
      "unit": "0", 
      "fill": "N"
    }, 
    {
      "count": 2, 
      "line_width": "8", 
      "convert": "0", 
      "shape": "path", 
      "path": [
        [
          200.0, 
          400.0
        ], 
        [
          200.0, 
          600.0
        ]
      ], 
      "de_morgan_alternate_shape": "0", 
      "unit": "0", 
      "fill": "N"
    }, 
    {
      "count": 2, 
      "line_width": "8", 
      "convert": "0", 
      "shape": "path", 
      "path": [
        [
          200.0, 
          600.0
        ], 
        [
          500.0, 
          600.0
        ]
      ], 
      "de_morgan_alternate_shape": "0", 
      "unit": "0", 
      "fill": "N"
    }, 
    {
      "count": 2, 
      "line_width": "8", 
      "convert": "0", 
      "shape": "path", 
      "path": [
        [
          -200.0, 
          1000.0
        ], 
        [
          -200.0, 
          400.0
        ]
      ], 
      "de_morgan_alternate_shape": "0", 
      "unit": "0", 
      "fill": "N"
    }, 
    {
      "count": 2, 
      "line_width": "8", 
      "convert": "0", 
      "shape": "path", 
      "path": [
        [
          -600.0, 
          400.0
        ], 
        [
          -300.0, 
          400.0
        ]
      ], 
      "de_morgan_alternate_shape": "0", 
      "unit": "0", 
      "fill": "N"
    }, 
    {
      "line_width": 8, 
      "start_angle": -1.5707963267948966, 
      "end_angle": 1.5707963267948966, 
      "shape": "arc", 
      "r": 49.0, 
      "counterclockwise": true, 
      "y": 450.0, 
      "x": -300.0, 
      "de_morgan_alternate_shape": "0", 
      "unit": "0", 
      "fill": "N"
    }, 
    {
      "line_width": 8, 
      "start_angle": -1.5707963267948966, 
      "end_angle": 1.5707963267948966, 
      "shape": "arc", 
      "r": 50.0, 
      "counterclockwise": true, 
      "y": 550.0, 
      "x": -300.0, 
      "de_morgan_alternate_shape": "0", 
      "unit": "0", 
      "fill": "N"
    }, 
    {
      "line_width": 8, 
      "start_angle": -1.5707963267948966, 
      "end_angle": 1.5707963267948966, 
      "shape": "arc", 
      "r": 50.0, 
      "counterclockwise": true, 
      "y": 650.0, 
      "x": -300.0, 
      "de_morgan_alternate_shape": "0", 
      "unit": "0", 
      "fill": "N"
    }, 
    {
      "line_width": 8, 
      "start_angle": -1.5707963267948966, 
      "end_angle": 1.5707963267948966, 
      "shape": "arc", 
      "r": 49.0, 
      "counterclockwise": true, 
      "y": 750.0, 
      "x": -300.0, 
      "de_morgan_alternate_shape": "0", 
      "unit": "0", 
      "fill": "N"
    }, 
    {
      "line_width": 8, 
      "start_angle": -1.5707963267948966, 
      "end_angle": 1.5707963267948966, 
      "shape": "arc", 
      "r": 49.0, 
      "counterclockwise": true, 
      "y": 850.0, 
      "x": -300.0, 
      "de_morgan_alternate_shape": "0", 
      "unit": "0", 
      "fill": "N"
    }, 
    {
      "line_width": 8, 
      "start_angle": -1.5707963267948966, 
      "end_angle": 1.5707963267948966, 
      "shape": "arc", 
      "r": 49.0, 
      "counterclockwise": true, 
      "y": 950.0, 
      "x": -300.0, 
      "de_morgan_alternate_shape": "0", 
      "unit": "0", 
      "fill": "N"
    }, 
    {
      "count": 2, 
      "line_width": "8", 
      "convert": "0", 
      "shape": "path", 
      "path": [
        [
          -300.0, 
          1000.0
        ], 
        [
          -600.0, 
          1000.0
        ]
      ], 
      "de_morgan_alternate_shape": "0", 
      "unit": "0", 
      "fill": "N"
    }, 
    {
      "count": 2, 
      "line_width": "8", 
      "convert": "0", 
      "shape": "path", 
      "path": [
        [
          -600.0, 
          700.0
        ], 
        [
          -300.0, 
          700.0
        ]
      ], 
      "de_morgan_alternate_shape": "0", 
      "unit": "0", 
      "fill": "N"
    }, 
    {
      "count": 2, 
      "line_width": "8", 
      "convert": "0", 
      "shape": "path", 
      "path": [
        [
          500.0, 
          400.0
        ], 
        [
          300.0, 
          400.0
        ]
      ], 
      "de_morgan_alternate_shape": "0", 
      "unit": "0", 
      "fill": "N"
    }, 
    {
      "count": 2, 
      "line_width": "8", 
      "convert": "0", 
      "shape": "path", 
      "path": [
        [
          300.0, 
          400.0
        ], 
        [
          300.0, 
          0.0
        ]
      ], 
      "de_morgan_alternate_shape": "0", 
      "unit": "0", 
      "fill": "N"
    }, 
    {
      "count": 2, 
      "line_width": "8", 
      "convert": "0", 
      "shape": "path", 
      "path": [
        [
          300.0, 
          0.0
        ], 
        [
          -100.0, 
          0.0
        ]
      ], 
      "de_morgan_alternate_shape": "0", 
      "unit": "0", 
      "fill": "N"
    }, 
    {
      "line_width": 8, 
      "start_angle": 1.5707963267948966, 
      "end_angle": -1.5707963267948966, 
      "shape": "arc", 
      "r": 50.0, 
      "counterclockwise": true, 
      "y": -50.0, 
      "x": -100.0, 
      "de_morgan_alternate_shape": "0", 
      "unit": "0", 
      "fill": "N"
    }, 
    {
      "line_width": 8, 
      "start_angle": 1.5707963267948966, 
      "end_angle": -1.5707963267948966, 
      "shape": "arc", 
      "r": 50.0, 
      "counterclockwise": true, 
      "y": -150.0, 
      "x": -100.0, 
      "de_morgan_alternate_shape": "0", 
      "unit": "0", 
      "fill": "N"
    }, 
    {
      "line_width": 8, 
      "start_angle": 1.5707963267948966, 
      "end_angle": -1.5707963267948966, 
      "shape": "arc", 
      "r": 50.0, 
      "counterclockwise": true, 
      "y": -250.0, 
      "x": -100.0, 
      "de_morgan_alternate_shape": "0", 
      "unit": "0", 
      "fill": "N"
    }, 
    {
      "line_width": 8, 
      "start_angle": 1.5707963267948966, 
      "end_angle": -1.5707963267948966, 
      "shape": "arc", 
      "r": 50.0, 
      "counterclockwise": true, 
      "y": -350.0, 
      "x": -100.0, 
      "de_morgan_alternate_shape": "0", 
      "unit": "0", 
      "fill": "N"
    }, 
    {
      "line_width": 8, 
      "start_angle": 1.5707963267948966, 
      "end_angle": -1.5707963267948966, 
      "shape": "arc", 
      "r": 49.0, 
      "counterclockwise": true, 
      "y": -450.0, 
      "x": -100.0, 
      "de_morgan_alternate_shape": "0", 
      "unit": "0", 
      "fill": "N"
    }, 
    {
      "line_width": 8, 
      "start_angle": 1.5707963267948966, 
      "end_angle": -1.5707963267948966, 
      "shape": "arc", 
      "r": 50.0, 
      "counterclockwise": true, 
      "y": -550.0, 
      "x": -100.0, 
      "de_morgan_alternate_shape": "0", 
      "unit": "0", 
      "fill": "N"
    }, 
    {
      "count": 2, 
      "line_width": "8", 
      "convert": "0", 
      "shape": "path", 
      "path": [
        [
          -600.0, 
          -600.0
        ], 
        [
          -300.0, 
          -600.0
        ]
      ], 
      "de_morgan_alternate_shape": "0", 
      "unit": "0", 
      "fill": "N"
    }, 
    {
      "line_width": 8, 
      "start_angle": -1.5707963267948966, 
      "end_angle": 1.5707963267948966, 
      "shape": "arc", 
      "r": 50.0, 
      "counterclockwise": true, 
      "y": -550.0, 
      "x": -300.0, 
      "de_morgan_alternate_shape": "0", 
      "unit": "0", 
      "fill": "N"
    }, 
    {
      "line_width": 8, 
      "start_angle": -1.5707963267948966, 
      "end_angle": 1.5707963267948966, 
      "shape": "arc", 
      "r": 49.0, 
      "counterclockwise": true, 
      "y": -450.0, 
      "x": -300.0, 
      "de_morgan_alternate_shape": "0", 
      "unit": "0", 
      "fill": "N"
    }, 
    {
      "line_width": 8, 
      "start_angle": -1.5707963267948966, 
      "end_angle": 1.5707963267948966, 
      "shape": "arc", 
      "r": 50.0, 
      "counterclockwise": true, 
      "y": -350.0, 
      "x": -300.0, 
      "de_morgan_alternate_shape": "0", 
      "unit": "0", 
      "fill": "N"
    }, 
    {
      "line_width": 8, 
      "start_angle": -1.5707963267948966, 
      "end_angle": 1.5707963267948966, 
      "shape": "arc", 
      "r": 50.0, 
      "counterclockwise": true, 
      "y": -250.0, 
      "x": -300.0, 
      "de_morgan_alternate_shape": "0", 
      "unit": "0", 
      "fill": "N"
    }, 
    {
      "line_width": 8, 
      "start_angle": -1.5707963267948966, 
      "end_angle": 1.5707963267948966, 
      "shape": "arc", 
      "r": 50.0, 
      "counterclockwise": true, 
      "y": -150.0, 
      "x": -300.0, 
      "de_morgan_alternate_shape": "0", 
      "unit": "0", 
      "fill": "N"
    }, 
    {
      "line_width": 8, 
      "start_angle": -1.5707963267948966, 
      "end_angle": 1.5707963267948966, 
      "shape": "arc", 
      "r": 50.0, 
      "counterclockwise": true, 
      "y": -50.0, 
      "x": -300.0, 
      "de_morgan_alternate_shape": "0", 
      "unit": "0", 
      "fill": "N"
    }, 
    {
      "count": 2, 
      "line_width": "8", 
      "convert": "0", 
      "shape": "path", 
      "path": [
        [
          -300.0, 
          0.0
        ], 
        [
          -600.0, 
          0.0
        ]
      ], 
      "de_morgan_alternate_shape": "0", 
      "unit": "0", 
      "fill": "N"
    }, 
    {
      "count": 2, 
      "line_width": "8", 
      "convert": "0", 
      "shape": "path", 
      "path": [
        [
          -200.0, 
          0.0
        ], 
        [
          -200.0, 
          -600.0
        ]
      ], 
      "de_morgan_alternate_shape": "0", 
      "unit": "0", 
      "fill": "N"
    }, 
    {
      "count": 2, 
      "line_width": "8", 
      "convert": "0", 
      "shape": "path", 
      "path": [
        [
          500.0, 
          -200.0
        ], 
        [
          300.0, 
          -200.0
        ]
      ], 
      "de_morgan_alternate_shape": "0", 
      "unit": "0", 
      "fill": "N"
    }, 
    {
      "count": 2, 
      "line_width": "8", 
      "convert": "0", 
      "shape": "path", 
      "path": [
        [
          300.0, 
          -200.0
        ], 
        [
          300.0, 
          -600.0
        ]
      ], 
      "de_morgan_alternate_shape": "0", 
      "unit": "0", 
      "fill": "N"
    }, 
    {
      "count": 2, 
      "line_width": "8", 
      "convert": "0", 
      "shape": "path", 
      "path": [
        [
          -100.0, 
          -600.0
        ], 
        [
          300.0, 
          -600.0
        ]
      ], 
      "de_morgan_alternate_shape": "0", 
      "unit": "0", 
      "fill": "N"
    }, 
    {
      "count": 2, 
      "line_width": "8", 
      "convert": "0", 
      "shape": "path", 
      "path": [
        [
          -300.0, 
          -300.0
        ], 
        [
          -600.0, 
          -300.0
        ]
      ], 
      "de_morgan_alternate_shape": "0", 
      "unit": "0", 
      "fill": "N"
    }, 
    {
      "count": 2, 
      "line_width": "16", 
      "convert": "0", 
      "shape": "path", 
      "path": [
        [
          700.0, 
          1100.0
        ], 
        [
          700.0, 
          -1100.0
        ]
      ], 
      "de_morgan_alternate_shape": "0", 
      "unit": "0", 
      "fill": "N"
    }, 
    {
      "count": 2, 
      "line_width": "16", 
      "convert": "0", 
      "shape": "path", 
      "path": [
        [
          700.0, 
          -1100.0
        ], 
        [
          500.0, 
          -1100.0
        ]
      ], 
      "de_morgan_alternate_shape": "0", 
      "unit": "0", 
      "fill": "N"
    }, 
    {
      "count": 2, 
      "line_width": "16", 
      "convert": "0", 
      "shape": "path", 
      "path": [
        [
          500.0, 
          -1100.0
        ], 
        [
          200.0, 
          -1100.0
        ]
      ], 
      "de_morgan_alternate_shape": "0", 
      "unit": "0", 
      "fill": "N"
    }, 
    {
      "count": 2, 
      "line_width": "16", 
      "convert": "0", 
      "shape": "path", 
      "path": [
        [
          200.0, 
          -1100.0
        ], 
        [
          -100.0, 
          -1100.0
        ]
      ], 
      "de_morgan_alternate_shape": "0", 
      "unit": "0", 
      "fill": "N"
    }, 
    {
      "count": 2, 
      "line_width": "16", 
      "convert": "0", 
      "shape": "path", 
      "path": [
        [
          -100.0, 
          -1100.0
        ], 
        [
          -400.0, 
          -1100.0
        ]
      ], 
      "de_morgan_alternate_shape": "0", 
      "unit": "0", 
      "fill": "N"
    }, 
    {
      "count": 2, 
      "line_width": "16", 
      "convert": "0", 
      "shape": "path", 
      "path": [
        [
          -400.0, 
          -1100.0
        ], 
        [
          -600.0, 
          -1100.0
        ]
      ], 
      "de_morgan_alternate_shape": "0", 
      "unit": "0", 
      "fill": "N"
    }, 
    {
      "count": 2, 
      "line_width": "16", 
      "convert": "0", 
      "shape": "path", 
      "path": [
        [
          -600.0, 
          -1100.0
        ], 
        [
          -600.0, 
          1100.0
        ]
      ], 
      "de_morgan_alternate_shape": "0", 
      "unit": "0", 
      "fill": "N"
    }, 
    {
      "count": 2, 
      "line_width": "16", 
      "convert": "0", 
      "shape": "path", 
      "path": [
        [
          -600.0, 
          1100.0
        ], 
        [
          100.0, 
          1100.0
        ]
      ], 
      "de_morgan_alternate_shape": "0", 
      "unit": "0", 
      "fill": "N"
    }, 
    {
      "count": 2, 
      "line_width": "16", 
      "convert": "0", 
      "shape": "path", 
      "path": [
        [
          100.0, 
          1100.0
        ], 
        [
          700.0, 
          1100.0
        ]
      ], 
      "de_morgan_alternate_shape": "0", 
      "unit": "0", 
      "fill": "N"
    }, 
    {
      "count": 2, 
      "line_width": "8", 
      "convert": "0", 
      "shape": "path", 
      "path": [
        [
          -200.0, 
          -950.0
        ], 
        [
          -100.0, 
          -950.0
        ]
      ], 
      "de_morgan_alternate_shape": "0", 
      "unit": "0", 
      "fill": "N"
    }, 
    {
      "count": 2, 
      "line_width": "8", 
      "convert": "0", 
      "shape": "path", 
      "path": [
        [
          -300.0, 
          -950.0
        ], 
        [
          -400.0, 
          -950.0
        ]
      ], 
      "de_morgan_alternate_shape": "0", 
      "unit": "0", 
      "fill": "N"
    }, 
    {
      "count": 2, 
      "line_width": "8", 
      "convert": "0", 
      "shape": "path", 
      "path": [
        [
          -400.0, 
          -950.0
        ], 
        [
          -400.0, 
          -1100.0
        ]
      ], 
      "de_morgan_alternate_shape": "0", 
      "unit": "0", 
      "fill": "N"
    }, 
    {
      "count": 2, 
      "line_width": "8", 
      "convert": "0", 
      "shape": "path", 
      "path": [
        [
          -100.0, 
          -950.0
        ], 
        [
          -100.0, 
          -1100.0
        ]
      ], 
      "de_morgan_alternate_shape": "0", 
      "unit": "0", 
      "fill": "N"
    }, 
    {
      "count": 2, 
      "line_width": "8", 
      "convert": "0", 
      "shape": "path", 
      "path": [
        [
          200.0, 
          -950.0
        ], 
        [
          200.0, 
          -1100.0
        ]
      ], 
      "de_morgan_alternate_shape": "0", 
      "unit": "0", 
      "fill": "N"
    }, 
    {
      "count": 2, 
      "line_width": "8", 
      "convert": "0", 
      "shape": "path", 
      "path": [
        [
          500.0, 
          -950.0
        ], 
        [
          500.0, 
          -1100.0
        ]
      ], 
      "de_morgan_alternate_shape": "0", 
      "unit": "0", 
      "fill": "N"
    }, 
    {
      "count": 2, 
      "line_width": "8", 
      "convert": "0", 
      "shape": "path", 
      "path": [
        [
          100.0, 
          700.0
        ], 
        [
          100.0, 
          1100.0
        ]
      ], 
      "de_morgan_alternate_shape": "0", 
      "unit": "0", 
      "fill": "N"
    }, 
    {
      "count": 2, 
      "line_width": "8", 
      "convert": "0", 
      "shape": "path", 
      "path": [
        [
          -100.0, 
          700.0
        ], 
        [
          -50.0, 
          700.0
        ]
      ], 
      "de_morgan_alternate_shape": "0", 
      "unit": "0", 
      "fill": "N"
    }, 
    {
      "count": 2, 
      "line_width": "8", 
      "convert": "0", 
      "shape": "path", 
      "path": [
        [
          -50.0, 
          750.0
        ], 
        [
          -50.0, 
          700.0
        ]
      ], 
      "de_morgan_alternate_shape": "0", 
      "unit": "0", 
      "fill": "N"
    }, 
    {
      "count": 2, 
      "line_width": "8", 
      "convert": "0", 
      "shape": "path", 
      "path": [
        [
          -50.0, 
          700.0
        ], 
        [
          -50.0, 
          650.0
        ]
      ], 
      "de_morgan_alternate_shape": "0", 
      "unit": "0", 
      "fill": "N"
    }, 
    {
      "count": 2, 
      "line_width": "8", 
      "convert": "0", 
      "shape": "path", 
      "path": [
        [
          0.0, 
          750.0
        ], 
        [
          0.0, 
          700.0
        ]
      ], 
      "de_morgan_alternate_shape": "0", 
      "unit": "0", 
      "fill": "N"
    }, 
    {
      "count": 2, 
      "line_width": "8", 
      "convert": "0", 
      "shape": "path", 
      "path": [
        [
          0.0, 
          700.0
        ], 
        [
          0.0, 
          650.0
        ]
      ], 
      "de_morgan_alternate_shape": "0", 
      "unit": "0", 
      "fill": "N"
    }, 
    {
      "count": 2, 
      "line_width": "8", 
      "convert": "0", 
      "shape": "path", 
      "path": [
        [
          0.0, 
          700.0
        ], 
        [
          100.0, 
          700.0
        ]
      ], 
      "de_morgan_alternate_shape": "0", 
      "unit": "0", 
      "fill": "N"
    }, 
    {
      "count": 2, 
      "line_width": "8", 
      "convert": "0", 
      "shape": "path", 
      "path": [
        [
          -300.0, 
          -850.0
        ], 
        [
          -200.0, 
          -950.0
        ]
      ], 
      "de_morgan_alternate_shape": "0", 
      "unit": "0", 
      "fill": "N"
    }, 
    {
      "count": 2, 
      "line_width": "8", 
      "convert": "0", 
      "shape": "path", 
      "path": [
        [
          -200.0, 
          -950.0
        ], 
        [
          -300.0, 
          -1050.0
        ]
      ], 
      "de_morgan_alternate_shape": "0", 
      "unit": "0", 
      "fill": "N"
    }, 
    {
      "count": 2, 
      "line_width": "8", 
      "convert": "0", 
      "shape": "path", 
      "path": [
        [
          -300.0, 
          -1050.0
        ], 
        [
          -300.0, 
          -950.0
        ]
      ], 
      "de_morgan_alternate_shape": "0", 
      "unit": "0", 
      "fill": "N"
    }, 
    {
      "count": 2, 
      "line_width": "8", 
      "convert": "0", 
      "shape": "path", 
      "path": [
        [
          -300.0, 
          -950.0
        ], 
        [
          -300.0, 
          -850.0
        ]
      ], 
      "de_morgan_alternate_shape": "0", 
      "unit": "0", 
      "fill": "N"
    }, 
    {
      "count": 2, 
      "line_width": "8", 
      "convert": "0", 
      "shape": "path", 
      "path": [
        [
          -200.0, 
          -850.0
        ], 
        [
          -200.0, 
          -950.0
        ]
      ], 
      "de_morgan_alternate_shape": "0", 
      "unit": "0", 
      "fill": "N"
    }, 
    {
      "count": 2, 
      "line_width": "8", 
      "convert": "0", 
      "shape": "path", 
      "path": [
        [
          -200.0, 
          -950.0
        ], 
        [
          -200.0, 
          -1050.0
        ]
      ], 
      "de_morgan_alternate_shape": "0", 
      "unit": "0", 
      "fill": "N"
    }, 
    {
      "count": 2, 
      "line_width": "8", 
      "convert": "0", 
      "shape": "path", 
      "path": [
        [
          -237.0, 
          -862.0
        ], 
        [
          -175.0, 
          -800.0
        ]
      ], 
      "de_morgan_alternate_shape": "0", 
      "unit": "0", 
      "fill": "N"
    }, 
    {
      "count": 2, 
      "line_width": "8", 
      "convert": "0", 
      "shape": "path", 
      "path": [
        [
          -175.0, 
          -800.0
        ], 
        [
          -175.0, 
          -825.0
        ]
      ], 
      "de_morgan_alternate_shape": "0", 
      "unit": "0", 
      "fill": "N"
    }, 
    {
      "count": 2, 
      "line_width": "8", 
      "convert": "0", 
      "shape": "path", 
      "path": [
        [
          -175.0, 
          -800.0
        ], 
        [
          -200.0, 
          -800.0
        ]
      ], 
      "de_morgan_alternate_shape": "0", 
      "unit": "0", 
      "fill": "N"
    }, 
    {
      "count": 2, 
      "line_width": "8", 
      "convert": "0", 
      "shape": "path", 
      "path": [
        [
          -275.0, 
          -825.0
        ], 
        [
          -212.0, 
          -762.0
        ]
      ], 
      "de_morgan_alternate_shape": "0", 
      "unit": "0", 
      "fill": "N"
    }, 
    {
      "count": 2, 
      "line_width": "8", 
      "convert": "0", 
      "shape": "path", 
      "path": [
        [
          -212.0, 
          -762.0
        ], 
        [
          -212.0, 
          -787.0
        ]
      ], 
      "de_morgan_alternate_shape": "0", 
      "unit": "0", 
      "fill": "N"
    }, 
    {
      "count": 2, 
      "line_width": "8", 
      "convert": "0", 
      "shape": "path", 
      "path": [
        [
          -212.0, 
          -762.0
        ], 
        [
          -237.0, 
          -762.0
        ]
      ], 
      "de_morgan_alternate_shape": "0", 
      "unit": "0", 
      "fill": "N"
    }, 
    {
      "count": 2, 
      "line_width": "8", 
      "convert": "0", 
      "shape": "path", 
      "path": [
        [
          400.0, 
          -950.0
        ], 
        [
          500.0, 
          -950.0
        ]
      ], 
      "de_morgan_alternate_shape": "0", 
      "unit": "0", 
      "fill": "N"
    }, 
    {
      "count": 2, 
      "line_width": "8", 
      "convert": "0", 
      "shape": "path", 
      "path": [
        [
          300.0, 
          -950.0
        ], 
        [
          200.0, 
          -950.0
        ]
      ], 
      "de_morgan_alternate_shape": "0", 
      "unit": "0", 
      "fill": "N"
    }, 
    {
      "count": 2, 
      "line_width": "8", 
      "convert": "0", 
      "shape": "path", 
      "path": [
        [
          300.0, 
          -850.0
        ], 
        [
          400.0, 
          -950.0
        ]
      ], 
      "de_morgan_alternate_shape": "0", 
      "unit": "0", 
      "fill": "N"
    }, 
    {
      "count": 2, 
      "line_width": "8", 
      "convert": "0", 
      "shape": "path", 
      "path": [
        [
          400.0, 
          -950.0
        ], 
        [
          300.0, 
          -1050.0
        ]
      ], 
      "de_morgan_alternate_shape": "0", 
      "unit": "0", 
      "fill": "N"
    }, 
    {
      "count": 2, 
      "line_width": "8", 
      "convert": "0", 
      "shape": "path", 
      "path": [
        [
          300.0, 
          -1050.0
        ], 
        [
          300.0, 
          -950.0
        ]
      ], 
      "de_morgan_alternate_shape": "0", 
      "unit": "0", 
      "fill": "N"
    }, 
    {
      "count": 2, 
      "line_width": "8", 
      "convert": "0", 
      "shape": "path", 
      "path": [
        [
          300.0, 
          -950.0
        ], 
        [
          300.0, 
          -850.0
        ]
      ], 
      "de_morgan_alternate_shape": "0", 
      "unit": "0", 
      "fill": "N"
    }, 
    {
      "count": 2, 
      "line_width": "8", 
      "convert": "0", 
      "shape": "path", 
      "path": [
        [
          400.0, 
          -850.0
        ], 
        [
          400.0, 
          -950.0
        ]
      ], 
      "de_morgan_alternate_shape": "0", 
      "unit": "0", 
      "fill": "N"
    }, 
    {
      "count": 2, 
      "line_width": "8", 
      "convert": "0", 
      "shape": "path", 
      "path": [
        [
          400.0, 
          -950.0
        ], 
        [
          400.0, 
          -1050.0
        ]
      ], 
      "de_morgan_alternate_shape": "0", 
      "unit": "0", 
      "fill": "N"
    }, 
    {
      "count": 2, 
      "line_width": "8", 
      "convert": "0", 
      "shape": "path", 
      "path": [
        [
          362.0, 
          -862.0
        ], 
        [
          425.0, 
          -800.0
        ]
      ], 
      "de_morgan_alternate_shape": "0", 
      "unit": "0", 
      "fill": "N"
    }, 
    {
      "count": 2, 
      "line_width": "8", 
      "convert": "0", 
      "shape": "path", 
      "path": [
        [
          425.0, 
          -800.0
        ], 
        [
          425.0, 
          -825.0
        ]
      ], 
      "de_morgan_alternate_shape": "0", 
      "unit": "0", 
      "fill": "N"
    }, 
    {
      "count": 2, 
      "line_width": "8", 
      "convert": "0", 
      "shape": "path", 
      "path": [
        [
          425.0, 
          -800.0
        ], 
        [
          400.0, 
          -800.0
        ]
      ], 
      "de_morgan_alternate_shape": "0", 
      "unit": "0", 
      "fill": "N"
    }, 
    {
      "count": 2, 
      "line_width": "8", 
      "convert": "0", 
      "shape": "path", 
      "path": [
        [
          325.0, 
          -825.0
        ], 
        [
          387.0, 
          -762.0
        ]
      ], 
      "de_morgan_alternate_shape": "0", 
      "unit": "0", 
      "fill": "N"
    }, 
    {
      "count": 2, 
      "line_width": "8", 
      "convert": "0", 
      "shape": "path", 
      "path": [
        [
          387.0, 
          -762.0
        ], 
        [
          387.0, 
          -787.0
        ]
      ], 
      "de_morgan_alternate_shape": "0", 
      "unit": "0", 
      "fill": "N"
    }, 
    {
      "count": 2, 
      "line_width": "8", 
      "convert": "0", 
      "shape": "path", 
      "path": [
        [
          387.0, 
          -762.0
        ], 
        [
          362.0, 
          -762.0
        ]
      ], 
      "de_morgan_alternate_shape": "0", 
      "unit": "0", 
      "fill": "N"
    }, 
    {
      "direction": "0", 
      "de_morgan_alternate_shape": "0", 
      "shape": "text", 
      "text": ">NAME", 
      "y": 1250.0, 
      "x": -600.0, 
      "direction_unit": "deci-degrees", 
      "type": "0", 
      "unit": "0", 
      "size": "70"
    }, 
    {
      "direction": "0", 
      "de_morgan_alternate_shape": "0", 
      "shape": "text", 
      "text": ">VALUE", 
      "y": 1150.0, 
      "x": -600.0, 
      "direction_unit": "deci-degrees", 
      "type": "0", 
      "unit": "0", 
      "size": "70"
    }, 
    {
      "direction": "0", 
      "de_morgan_alternate_shape": "0", 
      "shape": "text", 
      "text": "RJ45", 
      "y": 950.0, 
      "x": 400.0, 
      "direction_unit": "deci-degrees", 
      "type": "0", 
      "unit": "0", 
      "size": "50"
    }, 
    {
      "line_width": "8", 
      "shape": "circle", 
      "r": 55.0, 
      "y": 800.0, 
      "x": 500.0, 
      "de_morgan_alternate_shape": "0", 
      "unit": "0", 
      "fill": "N"
    }, 
    {
      "line_width": "8", 
      "shape": "circle", 
      "r": 55.0, 
      "y": 600.0, 
      "x": 500.0, 
      "de_morgan_alternate_shape": "0", 
      "unit": "0", 
      "fill": "N"
    }, 
    {
      "line_width": "8", 
      "shape": "circle", 
      "r": 55.0, 
      "y": 400.0, 
      "x": 500.0, 
      "de_morgan_alternate_shape": "0", 
      "unit": "0", 
      "fill": "N"
    }, 
    {
      "line_width": "8", 
      "shape": "circle", 
      "r": 55.0, 
      "y": 200.0, 
      "x": 500.0, 
      "de_morgan_alternate_shape": "0", 
      "unit": "0", 
      "fill": "N"
    }, 
    {
      "line_width": "8", 
      "shape": "circle", 
      "r": 55.0, 
      "y": 0.0, 
      "x": 500.0, 
      "de_morgan_alternate_shape": "0", 
      "unit": "0", 
      "fill": "N"
    }, 
    {
      "line_width": "8", 
      "shape": "circle", 
      "r": 55.0, 
      "y": -200.0, 
      "x": 500.0, 
      "de_morgan_alternate_shape": "0", 
      "unit": "0", 
      "fill": "N"
    }, 
    {
      "line_width": "8", 
      "shape": "circle", 
      "r": 55.0, 
      "y": -400.0, 
      "x": 500.0, 
      "de_morgan_alternate_shape": "0", 
      "unit": "0", 
      "fill": "N"
    }, 
    {
      "line_width": "8", 
      "shape": "circle", 
      "r": 55.0, 
      "y": -600.0, 
      "x": 500.0, 
      "de_morgan_alternate_shape": "0", 
      "unit": "0", 
      "fill": "N"
    }
  ], 
  "name": "CON-RJ45-F_HR911105A", 
  "reference": "U", 
  "text": [
    {
      "orientation": "H", 
      "reference": "U", 
      "hjustify": "C", 
      "number": 0, 
      "vjustify": "C", 
      "visible": false, 
      "bold": false, 
      "italic": false, 
      "y": "0", 
      "x": "0", 
      "size": "0"
    }, 
    {
      "orientation": "H", 
      "reference": "CON-RJ45-F_HR911105A", 
      "hjustify": "C", 
      "number": 1, 
      "vjustify": "C", 
      "visible": false, 
      "bold": false, 
      "italic": false, 
      "y": "0", 
      "x": "0", 
      "size": "0"
    }
  ], 
  "power_flag": "N", 
  "units_locked": "0", 
  "text_offset": "100", 
  "draw_pin_name": true, 
  "pin": [
    {
      "direction": "R", 
      "name": "1", 
      "number": "1", 
      "shape": null, 
      "visible": true, 
      "length": "200", 
      "text_size_number": "0", 
      "y": "1000", 
      "x": "-800", 
      "electrical_type": "B", 
      "de_morgan_alternate_shape": "0", 
      "text_size_name": "0", 
      "unit": "0"
    }, 
    {
      "direction": "R", 
      "name": "2", 
      "number": "2", 
      "shape": null, 
      "visible": true, 
      "length": "200", 
      "text_size_number": "0", 
      "y": "400", 
      "x": "-800", 
      "electrical_type": "B", 
      "de_morgan_alternate_shape": "0", 
      "text_size_name": "0", 
      "unit": "0"
    }, 
    {
      "direction": "R", 
      "name": "3", 
      "number": "3", 
      "shape": null, 
      "visible": true, 
      "length": "200", 
      "text_size_number": "0", 
      "y": "0", 
      "x": "-800", 
      "electrical_type": "B", 
      "de_morgan_alternate_shape": "0", 
      "text_size_name": "0", 
      "unit": "0"
    }, 
    {
      "direction": "R", 
      "name": "4", 
      "number": "4", 
      "shape": null, 
      "visible": true, 
      "length": "200", 
      "text_size_number": "0", 
      "y": "700", 
      "x": "-800", 
      "electrical_type": "B", 
      "de_morgan_alternate_shape": "0", 
      "text_size_name": "0", 
      "unit": "0"
    }, 
    {
      "direction": "R", 
      "name": "5", 
      "number": "5", 
      "shape": null, 
      "visible": true, 
      "length": "200", 
      "text_size_number": "0", 
      "y": "-300", 
      "x": "-800", 
      "electrical_type": "B", 
      "de_morgan_alternate_shape": "0", 
      "text_size_name": "0", 
      "unit": "0"
    }, 
    {
      "direction": "R", 
      "name": "6", 
      "number": "6", 
      "shape": null, 
      "visible": true, 
      "length": "200", 
      "text_size_number": "0", 
      "y": "-600", 
      "x": "-800", 
      "electrical_type": "B", 
      "de_morgan_alternate_shape": "0", 
      "text_size_name": "0", 
      "unit": "0"
    }, 
    {
      "direction": "U", 
      "name": "9", 
      "number": "9", 
      "shape": null, 
      "visible": true, 
      "length": "200", 
      "text_size_number": "0", 
      "y": "-1300", 
      "x": "-400", 
      "electrical_type": "B", 
      "de_morgan_alternate_shape": "0", 
      "text_size_name": "0", 
      "unit": "0"
    }, 
    {
      "direction": "U", 
      "name": "10", 
      "number": "10", 
      "shape": null, 
      "visible": true, 
      "length": "200", 
      "text_size_number": "0", 
      "y": "-1300", 
      "x": "-100", 
      "electrical_type": "B", 
      "de_morgan_alternate_shape": "0", 
      "text_size_name": "0", 
      "unit": "0"
    }, 
    {
      "direction": "U", 
      "name": "11", 
      "number": "11", 
      "shape": null, 
      "visible": true, 
      "length": "200", 
      "text_size_number": "0", 
      "y": "-1300", 
      "x": "500", 
      "electrical_type": "B", 
      "de_morgan_alternate_shape": "0", 
      "text_size_name": "0", 
      "unit": "0"
    }, 
    {
      "direction": "U", 
      "name": "12", 
      "number": "12", 
      "shape": null, 
      "visible": true, 
      "length": "200", 
      "text_size_number": "0", 
      "y": "-1300", 
      "x": "200", 
      "electrical_type": "B", 
      "de_morgan_alternate_shape": "0", 
      "text_size_name": "0", 
      "unit": "0"
    }, 
    {
      "direction": "D", 
      "name": "13", 
      "number": "13", 
      "shape": null, 
      "visible": true, 
      "length": "200", 
      "text_size_number": "0", 
      "y": "1300", 
      "x": "100", 
      "electrical_type": "B", 
      "de_morgan_alternate_shape": "0", 
      "text_size_name": "0", 
      "unit": "0"
    }, 
    {
      "direction": "D", 
      "name": "14", 
      "number": "14", 
      "shape": null, 
      "visible": true, 
      "length": "200", 
      "text_size_number": "0", 
      "y": "1300", 
      "x": "300", 
      "electrical_type": "B", 
      "de_morgan_alternate_shape": "0", 
      "text_size_name": "0", 
      "unit": "0"
    }
  ], 
  "draw_pin_number": true, 
  "unit_count": 2
}