{
  "library_name": "E50-25", 
  "layer": "15", 
  "attribute1": "00000000", 
  "art": [
    {
      "line_width": 60.0, 
      "startx": 8750.0, 
      "starty": 4800.0, 
      "endy": 4950.0, 
      "endx": 8600.0, 
      "layer": "21", 
      "shape": "segment"
    }, 
    {
      "line_width": 60.0, 
      "startx": 8550.0, 
      "starty": 5000.0, 
      "endy": 5000.0, 
      "endx": -7300.0, 
      "layer": "21", 
      "shape": "segment"
    }, 
    {
      "line_width": 60.0, 
      "startx": 8550.0, 
      "starty": -5000.0, 
      "endy": -4800.0, 
      "endx": 8750.0, 
      "layer": "21", 
      "shape": "segment"
    }, 
    {
      "line_width": 60.0, 
      "startx": 8750.0, 
      "starty": -4800.0, 
      "endy": 4800.0, 
      "endx": 8750.0, 
      "layer": "21", 
      "shape": "segment"
    }, 
    {
      "line_width": 60.0, 
      "startx": -9000.0, 
      "starty": -4800.0, 
      "endy": -5000.0, 
      "endx": -8800.0, 
      "layer": "21", 
      "shape": "segment"
    }, 
    {
      "line_width": 60.0, 
      "startx": -9000.0, 
      "starty": -4800.0, 
      "endy": 4800.0, 
      "endx": -9000.0, 
      "layer": "21", 
      "shape": "segment"
    }, 
    {
      "line_width": 60.0, 
      "startx": -8800.0, 
      "starty": -5000.0, 
      "endy": -5000.0, 
      "endx": -8200.0, 
      "layer": "21", 
      "shape": "segment"
    }, 
    {
      "line_width": 60.0, 
      "startx": -8000.0, 
      "starty": -4800.0, 
      "endy": -5000.0, 
      "endx": -8200.0, 
      "layer": "21", 
      "shape": "segment"
    }, 
    {
      "line_width": 60.0, 
      "startx": -8000.0, 
      "starty": -4800.0, 
      "endy": -4800.0, 
      "endx": -7500.0, 
      "layer": "21", 
      "shape": "segment"
    }, 
    {
      "line_width": 60.0, 
      "startx": -7300.0, 
      "starty": -5000.0, 
      "endy": -4800.0, 
      "endx": -7500.0, 
      "layer": "21", 
      "shape": "segment"
    }, 
    {
      "line_width": 60.0, 
      "startx": -7300.0, 
      "starty": -5000.0, 
      "endy": -5000.0, 
      "endx": 8550.0, 
      "layer": "21", 
      "shape": "segment"
    }, 
    {
      "line_width": 60.0, 
      "startx": -8000.0, 
      "starty": -4800.0, 
      "endy": -4600.0, 
      "endx": -8000.0, 
      "layer": "21", 
      "shape": "segment"
    }, 
    {
      "line_width": 60.0, 
      "startx": -7500.0, 
      "starty": -4800.0, 
      "endy": -4600.0, 
      "endx": -7500.0, 
      "layer": "21", 
      "shape": "segment"
    }, 
    {
      "line_width": 60.0, 
      "startx": -9000.0, 
      "starty": -4800.0, 
      "endy": -4800.0, 
      "endx": -8000.0, 
      "layer": "21", 
      "shape": "segment"
    }, 
    {
      "line_width": 60.0, 
      "startx": -8000.0, 
      "starty": -4600.0, 
      "endy": -4600.0, 
      "endx": -7500.0, 
      "layer": "21", 
      "shape": "segment"
    }, 
    {
      "line_width": 60.0, 
      "startx": -7500.0, 
      "starty": -4800.0, 
      "endy": -4800.0, 
      "endx": 8750.0, 
      "layer": "21", 
      "shape": "segment"
    }, 
    {
      "line_width": 120.0, 
      "startx": -7950.0, 
      "starty": -4750.0, 
      "endy": -4750.0, 
      "endx": -7550.0, 
      "layer": "21", 
      "shape": "segment"
    }, 
    {
      "line_width": 120.0, 
      "startx": -7950.0, 
      "starty": -4650.0, 
      "endy": -4650.0, 
      "endx": -7550.0, 
      "layer": "21", 
      "shape": "segment"
    }, 
    {
      "line_width": 120.0, 
      "startx": -8800.0, 
      "starty": -4950.0, 
      "endy": -4950.0, 
      "endx": -8200.0, 
      "layer": "21", 
      "shape": "segment"
    }, 
    {
      "line_width": 120.0, 
      "startx": -8900.0, 
      "starty": -4850.0, 
      "endy": -4850.0, 
      "endx": -8850.0, 
      "layer": "21", 
      "shape": "segment"
    }, 
    {
      "line_width": 120.0, 
      "startx": -8850.0, 
      "starty": -4850.0, 
      "endy": -4900.0, 
      "endx": -8850.0, 
      "layer": "21", 
      "shape": "segment"
    }, 
    {
      "line_width": 120.0, 
      "startx": -8850.0, 
      "starty": -4850.0, 
      "endy": -4850.0, 
      "endx": -8150.0, 
      "layer": "21", 
      "shape": "segment"
    }, 
    {
      "line_width": 120.0, 
      "startx": -8150.0, 
      "starty": -4850.0, 
      "endy": -4900.0, 
      "endx": -8150.0, 
      "layer": "21", 
      "shape": "segment"
    }, 
    {
      "line_width": 120.0, 
      "startx": -8150.0, 
      "starty": -4850.0, 
      "endy": -4850.0, 
      "endx": -8100.0, 
      "layer": "21", 
      "shape": "segment"
    }, 
    {
      "line_width": 120.0, 
      "startx": -7300.0, 
      "starty": -4950.0, 
      "endy": -4950.0, 
      "endx": 8550.0, 
      "layer": "21", 
      "shape": "segment"
    }, 
    {
      "line_width": 120.0, 
      "startx": -7400.0, 
      "starty": -4850.0, 
      "endy": -4850.0, 
      "endx": -7350.0, 
      "layer": "21", 
      "shape": "segment"
    }, 
    {
      "line_width": 120.0, 
      "startx": -7350.0, 
      "starty": -4850.0, 
      "endy": -4900.0, 
      "endx": -7350.0, 
      "layer": "21", 
      "shape": "segment"
    }, 
    {
      "line_width": 120.0, 
      "startx": -7350.0, 
      "starty": -4850.0, 
      "endy": -4850.0, 
      "endx": 8650.0, 
      "layer": "21", 
      "shape": "segment"
    }, 
    {
      "line_width": 60.0, 
      "startx": -9000.0, 
      "starty": 4800.0, 
      "endy": 4950.0, 
      "endx": -8850.0, 
      "layer": "21", 
      "shape": "segment"
    }, 
    {
      "line_width": 60.0, 
      "startx": -8800.0, 
      "starty": 5000.0, 
      "endy": 5000.0, 
      "endx": -8200.0, 
      "layer": "21", 
      "shape": "segment"
    }, 
    {
      "line_width": 60.0, 
      "startx": -8000.0, 
      "starty": 4800.0, 
      "endy": 4950.0, 
      "endx": -8150.0, 
      "layer": "21", 
      "shape": "segment"
    }, 
    {
      "line_width": 60.0, 
      "startx": -8000.0, 
      "starty": 4800.0, 
      "endy": 4800.0, 
      "endx": -7500.0, 
      "layer": "21", 
      "shape": "segment"
    }, 
    {
      "line_width": 60.0, 
      "startx": -7500.0, 
      "starty": 4800.0, 
      "endy": 4950.0, 
      "endx": -7350.0, 
      "layer": "21", 
      "shape": "segment"
    }, 
    {
      "line_width": 60.0, 
      "startx": -8000.0, 
      "starty": -4600.0, 
      "endy": 4750.0, 
      "endx": -8000.0, 
      "layer": "21", 
      "shape": "segment"
    }, 
    {
      "line_width": 60.0, 
      "startx": -7500.0, 
      "starty": -4600.0, 
      "endy": 4750.0, 
      "endx": -7500.0, 
      "layer": "21", 
      "shape": "segment"
    }, 
    {
      "line_width": 60.0, 
      "startx": -8850.0, 
      "starty": 4950.0, 
      "endy": 4950.0, 
      "endx": -8150.0, 
      "layer": "21", 
      "shape": "segment"
    }, 
    {
      "line_width": 60.0, 
      "startx": -8850.0, 
      "starty": 4950.0, 
      "endy": 5000.0, 
      "endx": -8800.0, 
      "layer": "21", 
      "shape": "segment"
    }, 
    {
      "line_width": 60.0, 
      "startx": -8150.0, 
      "starty": 4950.0, 
      "endy": 5000.0, 
      "endx": -8200.0, 
      "layer": "21", 
      "shape": "segment"
    }, 
    {
      "line_width": 60.0, 
      "startx": -8000.0, 
      "starty": 4750.0, 
      "endy": 4750.0, 
      "endx": -7500.0, 
      "layer": "21", 
      "shape": "segment"
    }, 
    {
      "line_width": 60.0, 
      "startx": -8000.0, 
      "starty": 4750.0, 
      "endy": 4780.0, 
      "endx": -8000.0, 
      "layer": "21", 
      "shape": "segment"
    }, 
    {
      "line_width": 60.0, 
      "startx": -7500.0, 
      "starty": 4750.0, 
      "endy": 4780.0, 
      "endx": -7500.0, 
      "layer": "21", 
      "shape": "segment"
    }, 
    {
      "line_width": 60.0, 
      "startx": -7350.0, 
      "starty": 4950.0, 
      "endy": 4950.0, 
      "endx": 8600.0, 
      "layer": "21", 
      "shape": "segment"
    }, 
    {
      "line_width": 60.0, 
      "startx": -7350.0, 
      "starty": 4950.0, 
      "endy": 5000.0, 
      "endx": -7300.0, 
      "layer": "21", 
      "shape": "segment"
    }, 
    {
      "line_width": 60.0, 
      "startx": -8800.0, 
      "starty": 5000.0, 
      "endy": 4980.0, 
      "endx": -8800.0, 
      "layer": "21", 
      "shape": "segment"
    }, 
    {
      "line_width": 60.0, 
      "startx": -8800.0, 
      "starty": 4980.0, 
      "endy": 4980.0, 
      "endx": -8200.0, 
      "layer": "21", 
      "shape": "segment"
    }, 
    {
      "line_width": 60.0, 
      "startx": -8000.0, 
      "starty": 4780.0, 
      "endy": 4780.0, 
      "endx": -7500.0, 
      "layer": "21", 
      "shape": "segment"
    }, 
    {
      "line_width": 60.0, 
      "startx": -8000.0, 
      "starty": 4780.0, 
      "endy": 4800.0, 
      "endx": -8000.0, 
      "layer": "21", 
      "shape": "segment"
    }, 
    {
      "line_width": 60.0, 
      "startx": -7500.0, 
      "starty": 4780.0, 
      "endy": 4800.0, 
      "endx": -7500.0, 
      "layer": "21", 
      "shape": "segment"
    }, 
    {
      "line_width": 60.0, 
      "startx": -7300.0, 
      "starty": 5000.0, 
      "endy": 4980.0, 
      "endx": -7300.0, 
      "layer": "21", 
      "shape": "segment"
    }, 
    {
      "line_width": 60.0, 
      "startx": -7300.0, 
      "starty": 4980.0, 
      "endy": 4980.0, 
      "endx": 8550.0, 
      "layer": "21", 
      "shape": "segment"
    }, 
    {
      "line_width": 60.0, 
      "startx": 8600.0, 
      "starty": 4950.0, 
      "endy": 5000.0, 
      "endx": 8550.0, 
      "layer": "21", 
      "shape": "segment"
    }, 
    {
      "line_width": 60.0, 
      "startx": -2400.0, 
      "starty": 600.0, 
      "endy": 600.0, 
      "endx": -2200.0, 
      "layer": "21", 
      "shape": "segment"
    }, 
    {
      "line_width": 60.0, 
      "startx": -2200.0, 
      "starty": 600.0, 
      "endy": -600.0, 
      "endx": -2200.0, 
      "layer": "21", 
      "shape": "segment"
    }, 
    {
      "line_width": 60.0, 
      "startx": -2200.0, 
      "starty": -600.0, 
      "endy": -600.0, 
      "endx": -2400.0, 
      "layer": "21", 
      "shape": "segment"
    }, 
    {
      "line_width": 60.0, 
      "startx": -2700.0, 
      "starty": -500.0, 
      "endy": -200.0, 
      "endx": -2700.0, 
      "layer": "21", 
      "shape": "segment"
    }, 
    {
      "line_width": 60.0, 
      "startx": -2850.0, 
      "starty": -350.0, 
      "endy": -350.0, 
      "endx": -2550.0, 
      "layer": "21", 
      "shape": "segment"
    }, 
    {
      "line_width": 60.0, 
      "startx": -2400.0, 
      "starty": -600.0, 
      "endy": 0.0, 
      "endx": -2400.0, 
      "layer": "21", 
      "shape": "segment"
    }, 
    {
      "line_width": 60.0, 
      "startx": -2400.0, 
      "starty": 0.0, 
      "endy": 600.0, 
      "endx": -2400.0, 
      "layer": "21", 
      "shape": "segment"
    }, 
    {
      "line_width": 60.0, 
      "startx": -1850.0, 
      "starty": 0.0, 
      "endy": 0.0, 
      "endx": 8250.0, 
      "layer": "21", 
      "shape": "segment"
    }, 
    {
      "line_width": 60.0, 
      "startx": -7000.0, 
      "starty": 0.0, 
      "endy": 0.0, 
      "endx": -2400.0, 
      "layer": "21", 
      "shape": "segment"
    }, 
    {
      "line_width": 300.0, 
      "startx": 9750.0, 
      "starty": 0.0, 
      "endy": 0.0, 
      "endx": 9000.0, 
      "layer": "25", 
      "shape": "segment"
    }, 
    {
      "line_width": 300.0, 
      "startx": -10000.0, 
      "starty": 0.0, 
      "endy": 0.0, 
      "endx": -9250.0, 
      "layer": "25", 
      "shape": "segment"
    }, 
    {
      "line_width": 50.0, 
      "startx": -2000.0, 
      "starty": 600.0, 
      "endy": 600.0, 
      "endx": -1800.0, 
      "layer": "21", 
      "shape": "segment"
    }, 
    {
      "line_width": 50.0, 
      "startx": -1800.0, 
      "starty": 600.0, 
      "endy": -600.0, 
      "endx": -1800.0, 
      "layer": "21", 
      "shape": "segment"
    }, 
    {
      "line_width": 50.0, 
      "startx": -1800.0, 
      "starty": -600.0, 
      "endy": -600.0, 
      "endx": -2000.0, 
      "layer": "21", 
      "shape": "segment"
    }, 
    {
      "line_width": 50.0, 
      "startx": -2000.0, 
      "starty": -600.0, 
      "endy": 600.0, 
      "endx": -2000.0, 
      "layer": "21", 
      "shape": "segment"
    }, 
    {
      "line_width": 50.0, 
      "startx": 8750.0, 
      "starty": 150.0, 
      "endy": 150.0, 
      "endx": 8950.0, 
      "layer": "21", 
      "shape": "segment"
    }, 
    {
      "line_width": 50.0, 
      "startx": 8950.0, 
      "starty": 150.0, 
      "endy": -150.0, 
      "endx": 8950.0, 
      "layer": "21", 
      "shape": "segment"
    }, 
    {
      "line_width": 50.0, 
      "startx": 8950.0, 
      "starty": -150.0, 
      "endy": -150.0, 
      "endx": 8750.0, 
      "layer": "21", 
      "shape": "segment"
    }, 
    {
      "line_width": 50.0, 
      "startx": 8750.0, 
      "starty": -150.0, 
      "endy": 150.0, 
      "endx": 8750.0, 
      "layer": "21", 
      "shape": "segment"
    }, 
    {
      "line_width": 50.0, 
      "startx": -9200.0, 
      "starty": 150.0, 
      "endy": 150.0, 
      "endx": -9000.0, 
      "layer": "21", 
      "shape": "segment"
    }, 
    {
      "line_width": 50.0, 
      "startx": -9000.0, 
      "starty": 150.0, 
      "endy": -150.0, 
      "endx": -9000.0, 
      "layer": "21", 
      "shape": "segment"
    }, 
    {
      "line_width": 50.0, 
      "startx": -9000.0, 
      "starty": -150.0, 
      "endy": -150.0, 
      "endx": -9200.0, 
      "layer": "21", 
      "shape": "segment"
    }, 
    {
      "line_width": 50.0, 
      "startx": -9200.0, 
      "starty": -150.0, 
      "endy": 150.0, 
      "endx": -9200.0, 
      "layer": "21", 
      "shape": "segment"
    }
  ], 
  "name": "E50-25", 
  "keyword": [
    " <b>ELECTROLYTIC CAPACITOR</b><p>"
  ], 
  "text": [
    {
      "layer": "26", 
      "angle": 0.0, 
      "misc": " \">NAME\"", 
      "sizex": 700.0, 
      "number": "0", 
      "sizey": 700.0, 
      "visible": true, 
      "flag": "N", 
      "text": ">NAME", 
      "y": -4850.0, 
      "x": -7300.0, 
      "rotation": "0", 
      "penwidth": 70.0
    }, 
    {
      "layer": "26", 
      "angle": 0.0, 
      "misc": " \">VALUE\"", 
      "sizex": 700.0, 
      "number": "1", 
      "sizey": 700.0, 
      "visible": true, 
      "flag": "N", 
      "text": ">VALUE", 
      "y": 1330.0, 
      "x": 610.0, 
      "rotation": "0", 
      "penwidth": 70.0
    }
  ], 
  "timestamp_op": "00000000", 
  "rotation_cost_180": "0", 
  "attribute2": "~~", 
  "y": 0.0, 
  "rotation_cost_misc": "0", 
  "pad": [
    {
      "angle": 0.0, 
      "name": "+", 
      "drill_diam": 440.0, 
      "deltax": 0.0, 
      "deltay": 0.0, 
      "sizex": 1500.0, 
      "sizey": 1500.0, 
      "drill_x": 0.0, 
      "layer_mask": "00C0FFFF", 
      "shape": "oblong", 
      "drill_y": 0.0, 
      "posy": 0.0, 
      "posx": -10000.0, 
      "shape_code": "O", 
      "type": "STD", 
      "drill_shape": "circle", 
      "orientation": 0
    }, 
    {
      "angle": 0.0, 
      "name": "-", 
      "drill_diam": 440.0, 
      "deltax": 0.0, 
      "deltay": 0.0, 
      "sizex": 1500.0, 
      "sizey": 1500.0, 
      "drill_x": 0.0, 
      "layer_mask": "00C0FFFF", 
      "shape": "oblong", 
      "drill_y": 0.0, 
      "posy": 0.0, 
      "posx": 9750.0, 
      "shape_code": "O", 
      "type": "STD", 
      "drill_shape": "circle", 
      "orientation": 0
    }
  ], 
  "timestamp": "00000000", 
  "units": "deci-mils", 
  "x": 0.0, 
  "rotation_cost_90": "0", 
  "angle": 0.0, 
  "orientation": "0"
}